Workbook
Name Admin_Cost_per_day: #REF!
Name Admin.costperday: #REF!
Name Admin.costperroom: #REF!
Name Buffet_Breakfast_cost_per_room: #REF!
Name buffet.breakfas.costperroom: #REF!
Name Contribution_margin_per_unit: [1]Model!$C$4
Name Cost_of_parts_per_unit: [1]Model!$H$5
Name Daily_Miscellaneous_expense: #REF!
Name daily_miscellaneous_expense1: #REF!
Name daily_miscellaneous_expenses: #REF!
Name Daily_Online_Reservation: #REF!
Name daily_online_reservation1: #REF!
Name daily_online_reservations: #REF!
Name daily.miscellaneous.expense: #REF!
Name daily.online.reservation: #REF!
Name Demand: [1]Model!$H$6
Name Direct_labour_cost_per_unit: [1]Model!$H$4
Name First_year_profit: [1]Model!$C$6
Name House_Keeping_Cost_per_room: #REF!
Name Housekeeping.costperroom: #REF!
Name Late_Cancellation_Fee: #REF!
Name late_cancellation_fee1: #REF!
Name late_cancellation1: #REF!
Name Late_Cancellations: #REF!
Name late.cancellation: #REF!
Name late.cancellation.fee: #REF!
Name Marketing_Cost_per_day: #REF!
Name Marketing.costperday: #REF!
Name Marketing.costperroom: #REF!
Name No_of_Rooms: #REF!
Name no.of.rooms: #REF!
Name Number_of_Room_occupied: #REF!
Name number_of_walkins: #REF!
Name Number_of_walkins_accepted: #REF!
Name numberof.roomsoccupied: #REF!
Name numberof.walkinsaccepted: #REF!
Name Occupancy_Rate: #REF!
Name occupancyrate: #REF!
Name Overbooking_fee: #REF!
Name Overbooking_Rate: #REF!
Name overbooking_rate1: #REF!
Name Overbooking.fee: #REF!
Name overbooking.rate: #REF!
Name Room_Rate: #REF!
Name room_rate1: #REF!
Name room.rate: #REF!
Name Rooms_Overbooked: #REF!
Name roomsoverbooked: #REF!
Name Sales_Revenue_Per_day: #REF!
Name salesrevenue.perday: #REF!
Name sold.out: #REF!
Name Total_Cost_per_day: #REF!
Name Total_Profit: #REF!
Name Total.daily.profit: #REF!
Name Totalcost.perday: #REF!
Name Walk_Ins: #REF!
Name walk.ins: #REF!
Name walkin1: #REF!
Name Welcome_Pack_cost_per_room: #REF!
Name welcomepack.costperroom: #REF!

Sheet 1.a Manager's Page
A3: Stochastic inputs | C3: Desription and assumption
A4: S Input 1 | B4: Daily online reservations | C4: Number of booking requests made one day in advance. For a boutique costal property in peak season, it is assumed average advance reservation fill approximately 90% of capacity at baseline price of $150. Dependent on nightly room price. Price at $120 increases demand by 20%, and price at $120 decreases demand by 60%
A5: S Input 2 | B5: Late cancellations percentage | C5: Portions of thoese advance reservations that on or after their scheduled arrival date (no show). Late cancellations are assumed to average 15% of advance bookings but can vary from as low as 5% during reliable periods to as high as 25% when external disruptions occur
A6: S Input 3 | B6: Walk-in arrivals | C6: Guests arriving without a prior reservation. Walk-in arrivals are assumed at around a base of 3 per day, ranging from 0 when rooms sell out in advance to 8 or event-driven surge days
A7: S Input 4 | B7: Miscellaneuous daily expenses | C7: Unplanned operating costs such as last-minute maintenance, guest amenity requests, small repairs and emergency staff overtime. Ranging from $100 to $600 per day
A9: Decision variables | C9: Desription and assumption
A10: D Variable 1 | B10: Room nightly rate ($) | C10: Three tiered price points. Higher price -> higher revenue but may reduce bookings
A11: D Variable 2 | B11: Over-booking level | C11: Allows selling more than capacity to hedge against cancellations. Bumped guests incur compensation cost
A12: D Variable 3 | B12: Late-cancellation fee (%) | C12: Fee charged if guest cancels late. Offets some no-show lost; may reduce cancellations if fee > 0.
A14: Fixed inputs | C14: Desription and assumption
A15: F Input 1 | B15: Total rooms available | C15: Total one-bed unit at Coastal Nest with 20 rooms
A16: F Input 2 | B16: Housekeeping cost per occupied | C16: Deep turnover clean including 1.5 h of labor at $30/hr ($45) plus $5 for laundry, linens and consumables—reflective of boutique Airbnb‐style standards.
A17: F Input 3 | B17: Utilities cost per occupied room | C17: Average daily cost for electricity, water, Heating ventilation and air conditioning (HVAC) per occupied room
A18: F Input 4 | B18: Management and marketing fee per occupied room | C18: Allocated slice of on-site leadership and promotion spent per room-night. Assumption: There is one operation manager (100k AUD/year) and one marketing manager (110k AUD/year), with the marketing manager spending only 50% of time on Coastal Net Motel. Their combined allocated cost is approximately $425/day spreading over 20 rooms, which yields $21.25, rounded to $20.
A19: F Input 5 | B19: Check-in staff cost per day | C19: Covers 8 hours of front-desk/host time (morning check-out/check-in overlap + evening guest support) at $25/hour fully-loaded.
A21: CALCULATED VALUES | C21: Desription and assumption
A22: C Value 1 | B22: Net demand | C22: The total number of guests who actually show up and want a room on a given day. Assumption: - Some advance bookings cancel at the last minute (no-shows). - Walk-in guests then show up independently. Formula: Max(Daily Online Reservation - Round(Daily Online Reservation * Late Cancellation Portion,0),0) + Walk-in Arrivals
A23: C Value 2 | B23: Room sold | C23: How many rooms that the motel actually sells on a given day (including intentional over-booking). Capped by over-booking policy. Assumptions: - Never confirm more than Total room * (1 + Over-booking percentage) bookings. - Even if demand is higher, stop selling at that cap. Formula: Min(Net Demand, Round (Total Rooms * (1 + Over-booking level),0)
A24: C Value 3 | B24: Bumped guests | C24: The number of confirmed guest the motel must turn away or re-room because the motel over-booked and too many showed up. Assumption: - Physical limit is total number of room. - Anyone above the limit gets bumped and compensated. Formula: Max(Rooms Sold - Total Rooms, 0)
A25: C Value 4 | B25: Revenue from stays | C25: The income earned from rooms actually occupied Assumption: All paying guests (bookings that weren't bumped) pay the full nightly rate Formula: Room Sold x Room Nightly Rate
A26: C Value 5 | B26: Total compensation cost | C26: The expense of relocating or compensating guests the motel has bumped Assumptions: Every bumped guest gets exactly one night's Rom Nightly Rate in compensation Formula: Bumped Guests x Room Nightly Rate
A27: C Value 6 | B27: Total housekeeping cost | C27: The cost of cleaning and servicing each occupied room Assumptions: Unit house keeping cost is constant per occupied room. Only physical room (not bumped) incur this cost (up to Total room) Formula: Bumped Guests x Room Nightly Rate
A28: C Value 7 | B28: Total utilities cost | C28: Electricity, water, HVAC expenses per occupied room. Assumptions: Unit utilities cost applies per occupied room. Same occupancy basis as housekeeping Formula: Utilities Cost per Occupied Room x min(Net demand, total rooms)
A29: C Value 8 | B29: Total fixed inputs cost | C29: Sum of all day-to-day costs that vary with occupancy or bumping. Formula: Housekeeping Cost + Utilities cost + Compensation cost + Management and Marketing Fee + Miscellaneous expense
A30: C Value 9 | B30: Late no shows | C30: Number of advance booking that fail to materialise on arrival day. Formula: Round(Online Daily Booking * Late Cancellation Portions,0)
A31: C Value 10 | B31: Late cancellation fee revenue | C31: Penalty income from same-day cancellation (No-shows). Assumptions: Motel charges a percentage of the nightly rate on each no-show. This is separate from full room revenue. Formula: Late No Shows * Room Nightly Rate * Cancellation Fee
B33: OUTPUT
B34: Total Daily Profit | C34: The bottom-line profit for the day
B35: Sold Out: Yes/ No | C35: Yest if the Net Demand >= total rooms and over-booking sold out capcity; No otherwise
B38: General Assumption
B39: Length of stay per reservation | C39: Every booking covers exactly one night. Multi-night stays are not modelled
B40: Homogeneous rooms | C40: All rooms are identical in size, amenities, and nightly rate
B41: One-day booking lead time | C41: All advanced bookings occur exactly one day before arrival (no bookings further out)
B42: Instant cancellation | C42: Late cancellations occur on arrival day and immediately free up capacity for walk-ins
B43: Walk-ins only on no-show days | C43: Walk-in guest only fill the rooms freed by cancellations (or extra over-booking slots)
B44: No group or bulk bookings | C44: Every booking (in advance or walk-in) is for a single room
B45: Fixed housekeeping and utilities costs | C45: Each occupied room costs the same to clean and service, regardless of overall occupancy
B46: Compensation cost is equivalent to one night's rate | C46: Any bumped guest triggers the same compensation amount they are charged for one night
B47: No fixed overheads | C47: Only variable costs (housekeeping, utilities, compensation, misc. expenses) are modeled; fixed overheads (management salaries, property taxes) are excluded from daily profit

Sheet 1.b Model_Best estimates
G2: INPUTS
B3: CALCULATED VALUES & OUTPUT (DAILY) | C3: values | G3: Stochastic inputs | H3: values | L3: =G3 -> Stochastic inputs | M3: Worst Case | N3: Base Case | O3: Best Case
B4: ='1.a Manager''s Page'!B22 -> Net demand | C4: =ROUND(MAX(H4-ROUND(H4*H5,0),0)+H6,0) -> 18 | G4: ='1.a Manager''s Page'!B4 -> Daily online reservations | H4: {=ROUND(_xlfn.IFS(H16=120,18*1.2,H16=150,18,H16=180,18*0.4),0)} -> 18 | I4: Best guess | L4: =G4 -> Daily online reservations | M4: 7 bookings | N4: 18 bookings | O4: 22 bookings
B5: ='1.a Manager''s Page'!B23 -> Room sold | C5: =MIN(C4,ROUND(H24*(1+H17),0)) -> 18 | G5: ='1.a Manager''s Page'!B5 -> Late cancellations percentage | H5: 0.15 | I5: Best guess | L5: =G5 -> Late cancellations percentage | M5: 25% of bookings | N5: 15% bookings | O5: 5% bookings
B6: ='1.a Manager''s Page'!B24 -> Bumped guests | C6: =MAX(C5-H24,0) -> 0 | G6: ='1.a Manager''s Page'!B6 -> Walk-in arrivals | H6: 3 | I6: Best guess | L6: =G6 -> Walk-in arrivals | M6: 1 guests/day | N6: 3 guests/day | O6: 8 guests/day
B7: ='1.a Manager''s Page'!B25 -> Revenue from stays | C7: =C5*H16 -> 2700 | G7: ='1.a Manager''s Page'!B7 -> Miscellaneuous daily expenses | H7: 300 | I7: Best guess | L7: =G7 -> Miscellaneuous daily expenses | M7: $600/day | N7: $300/day | O7: $100/day
B8: ='1.a Manager''s Page'!B26 -> Total compensation cost | C8: =C6*H16 -> 0
B9: ='1.a Manager''s Page'!B27 -> Total housekeeping cost | C9: =H25*MIN(C5,H24) -> 900
B10: ='1.a Manager''s Page'!B28 -> Total utilities cost | C10: =H26*MIN(C4,H24) -> 270
B12: ='1.a Manager''s Page'!B29 -> Total fixed inputs cost | C12: =C8+C9+C10+H7+H28+H27 -> 2095
B13: ='1.a Manager''s Page'!B30 -> Late no shows | C13: =ROUND(H4*H5,0) -> 3
B14: ='1.a Manager''s Page'!B31 -> Late cancellation fee revenue | C14: =C13*H16*H18 -> 45
G15: Decision variables | H15: values
B16: OUTPUT | G16: ='1.a Manager''s Page'!B10 -> Room nightly rate ($) | H16: 150
B17: Total Daily Profit | C17: =C7+C14-C12 -> 650 | G17: ='1.a Manager''s Page'!B11 -> Over-booking level | H17: 0.1
B18: Sold Out: Yes/ No | C18: =IF(C5>=H24,"Yes","No") -> No | G18: ='1.a Manager''s Page'!B12 -> Late-cancellation fee (%) | H18: 0.1
G23: Fixed inputs | H23: values
G24: ='1.a Manager''s Page'!B15 -> Total rooms available | H24: 20
G25: ='1.a Manager''s Page'!B16 -> Housekeeping cost per occupied | H25: 50
G26: ='1.a Manager''s Page'!B17 -> Utilities cost per occupied room | H26: 15
G27: ='1.a Manager''s Page'!B18 -> Management and marketing fee per occupied room | H27: 425
G28: ='1.a Manager''s Page'!B19 -> Check-in staff cost per day | H28: 200

Sheet 1.c Model Simulated data
G2: INPUTS
B3: CALCULATED VALUES & OUTPUT (DAILY) | C3: values | G3: Stochastic inputs | H3: values
B4: ='1.a Manager''s Page'!B22 -> Net demand | C4: =ROUND(MAX(H4-ROUND(H4*H5,0),0)+H6,0) -> 13 | G4: ='1.a Manager''s Page'!B4 -> Daily online reservations | H4: {=_xlfn.IFS(H16=120,'3.b Probability Distributions'!D15,H16=150,'3.b Probability Distributions'!D16,H16=180,'3.b Probability Distributions'!D17)} -> 5.8277105
B5: ='1.a Manager''s Page'!B23 -> Room sold | C5: =MIN(C4,ROUND(H24*(1+H17),0)) -> 13 | G5: ='1.a Manager''s Page'!B5 -> Late cancellations percentage | H5: =VLOOKUP(RAND(),'3.b Probability Distributions'!$N$6:$P$10,3,TRUE) -> 0.25
B6: ='1.a Manager''s Page'!B24 -> Bumped guests | C6: =MAX(C5-H24,0) -> 0 | G6: ='1.a Manager''s Page'!B6 -> Walk-in arrivals | H6: =VLOOKUP(RAND(),'3.b Probability Distributions'!$X$6:$Z$16,3,TRUE) -> 8
B7: ='1.a Manager''s Page'!B25 -> Revenue from stays | C7: =C5*H16 -> 2340 | G7: ='1.a Manager''s Page'!B7 -> Miscellaneuous daily expenses | H7: =ROUND('3.b Probability Distributions'!AH9,0) -> 454
B8: ='1.a Manager''s Page'!B26 -> Total compensation cost | C8: =C6*H16 -> 0
B9: ='1.a Manager''s Page'!B27 -> Total housekeeping cost | C9: =H25*MIN(C5,H24) -> 650
B10: ='1.a Manager''s Page'!B28 -> Total utilities cost | C10: =H26*MIN(C4,H24) -> 195
B12: ='1.a Manager''s Page'!B29 -> Total fixed inputs cost | C12: =C8+C9+C10+H7+H28+H27 -> 1924
B13: ='1.a Manager''s Page'!B30 -> Late no shows | C13: =ROUND(H4*H5,0) -> 1
B14: ='1.a Manager''s Page'!B31 -> Late cancellation fee revenue | C14: =C13*H16*H18 -> 18
G15: Decision variables | H15: values
B16: OUTPUT | G16: ='1.a Manager''s Page'!B10 -> Room nightly rate ($) | H16: 180
B17: Total Daily Profit | C17: =C7+C14-C12 -> 434 | G17: ='1.a Manager''s Page'!B11 -> Over-booking level | H17: 0.1
B18: Sold Out: Yes/ No | C18: =IF(C5>=H24,"Yes","No") -> No | G18: ='1.a Manager''s Page'!B12 -> Late-cancellation fee (%) | H18: 0.1
G23: Fixed inputs | H23: values
G24: ='1.a Manager''s Page'!B15 -> Total rooms available | H24: 20
G25: ='1.a Manager''s Page'!B16 -> Housekeeping cost per occupied | H25: 50
G26: ='1.a Manager''s Page'!B17 -> Utilities cost per occupied room | H26: 15
G27: ='1.a Manager''s Page'!B18 -> Management and marketing fee per occupied room | H27: 425
G28: ='1.a Manager''s Page'!B19 -> Check-in staff cost per day | H28: 200

Sheet 2.a.1 Scenario for S input 1
B1: ='1.b Model_Best estimates'!G16 -> Room nightly rate ($) | C1: 120 | I1: ='1.b Model_Best estimates'!G16 -> Room nightly rate ($) | K1: 150 | P1: ='1.b Model_Best estimates'!G16 -> Room nightly rate ($) | R1: 180
B2: Scenario Summary | I2: Scenario Summary | P2: Scenario Summary
D3: Current Values: | E3: Best Case | F3: Base Case | G3: Worst Case | K3: Current Values: | L3: Best Case | M3: Base Case | N3: Worst Case | R3: Current Values: | S3: Best Case | T3: Base Case | U3: Worst Case
E4: Created by Microsoft Office User on 5/19/2025 Modified by BA HUY HOANG LE on 21/05/2025 | F4: Created by Microsoft Office User on 5/19/2025 Modified by BA HUY HOANG LE on 21/05/2025 | G4: Created by Microsoft Office User on 5/19/2025 Modified by BA HUY HOANG LE on 21/05/2025 | L4: Created by Microsoft Office User on 5/19/2025 Modified by BA HUY HOANG LE on 21/05/2025 | M4: Created by Microsoft Office User on 5/19/2025 Modified by BA HUY HOANG LE on 21/05/2025 | N4: Created by Microsoft Office User on 5/19/2025 Modified by BA HUY HOANG LE on 21/05/2025 | S4: Created by Microsoft Office User on 5/19/2025 Modified by BA HUY HOANG LE on 21/05/2025 | T4: Created by Microsoft Office User on 5/19/2025 Modified by BA HUY HOANG LE on 21/05/2025 | U4: Created by Microsoft Office User on 5/19/2025 Modified by BA HUY HOANG LE on 21/05/2025
B5: Changing Cells: | I5: Changing Cells: | P5: Changing Cells:
C6: ='1.b Model_Best estimates'!G4 -> Daily online reservations | D6: 18 | E6: 22 | F6: 18 | G6: 7 | J6: ='1.b Model_Best estimates'!G4 -> Daily online reservations | K6: 18 | L6: 22 | M6: 18 | N6: 7 | Q6: ='1.b Model_Best estimates'!G4 -> Daily online reservations | R6: 18 | S6: 22 | T6: 18 | U6: 7
B7: Result Cells: | I7: Result Cells: | P7: Result Cells:
C8: ='1.b Model_Best estimates'!B17 -> Total Daily Profit | D8: 211 | E8: 211 | F8: 211 | G8: -143 | J8: ='1.b Model_Best estimates'!B17 -> Total Daily Profit | K8: 735 | L8: 820 | M8: 735 | N8: -60 | Q8: ='1.b Model_Best estimates'!B17 -> Total Daily Profit | R8: 969 | S8: 1429 | T8: 969 | U8: -102
B13: ='1.b Model_Best estimates'!G16 -> Room nightly rate ($) | C13: 120 | I13: ='1.b Model_Best estimates'!G16 -> Room nightly rate ($) | K13: 150 | P13: ='1.b Model_Best estimates'!G16 -> Room nightly rate ($) | R13: 180
B14: Scenario Summary | I14: Scenario Summary | P14: Scenario Summary
D15: Current Values: | E15: Best Case | F15: Base Case | G15: Worst Case | K15: Current Values: | L15: Best Case | M15: Base Case | N15: Worst Case | R15: Current Values: | S15: Best Case | T15: Base Case | U15: Worst Case
B16: Changing Cells: | I16: Changing Cells: | P16: Changing Cells:
C17: ='1.b Model_Best estimates'!G4 -> Daily online reservations | D17: 18 | E17: 22 | F17: 18 | G17: 7 | J17: ='1.b Model_Best estimates'!G4 -> Daily online reservations | K17: 18 | L17: 22 | M17: 18 | N17: 7 | Q17: ='1.b Model_Best estimates'!G4 -> Daily online reservations | R17: 18 | S17: 22 | T17: 18 | U17: 7
B18: Result Cells: | I18: Result Cells: | P18: Result Cells:
C19: ='1.b Model_Best estimates'!B18 -> Sold Out: Yes/ No | D19: Yes | E19: Yes | F19: Yes | G19: No | J19: ='1.b Model_Best estimates'!B18 -> Sold Out: Yes/ No | K19: No | L19: Yes | M19: No | N19: No | Q19: ='1.b Model_Best estimates'!B18 -> Sold Out: Yes/ No | R19: No | S19: Yes | T19: No | U19: No

Sheet 2.a.2 Scenario for S input 2
B1: ='1.b Model_Best estimates'!G16 -> Room nightly rate ($) | C1: 120 | I1: ='1.b Model_Best estimates'!G16 -> Room nightly rate ($) | J1: 150 | P1: ='1.b Model_Best estimates'!G16 -> Room nightly rate ($) | Q1: 180
B2: Scenario Summary | I2: Scenario Summary | P2: Scenario Summary
D3: Current Values: | E3: Best Case | F3: Base Case | G3: Worst Case | K3: Current Values: | L3: Best Case | M3: Base Case | N3: Worst Case | R3: Current Values: | S3: Best Case | T3: Base Case | U3: Worst Case
E4: Created by Microsoft Office User on 5/19/2025 Modified by BA HUY HOANG LE on 21/05/2025 | F4: Created by Microsoft Office User on 5/19/2025 Modified by BA HUY HOANG LE on 21/05/2025 | G4: Created by Microsoft Office User on 5/19/2025 Modified by BA HUY HOANG LE on 21/05/2025 | L4: Created by Microsoft Office User on 5/19/2025 Modified by BA HUY HOANG LE on 21/05/2025 | M4: Created by Microsoft Office User on 5/19/2025 Modified by BA HUY HOANG LE on 21/05/2025 | N4: Created by Microsoft Office User on 5/19/2025 Modified by BA HUY HOANG LE on 21/05/2025 | S4: Created by Microsoft Office User on 5/19/2025 Modified by BA HUY HOANG LE on 21/05/2025 | T4: Created by Microsoft Office User on 5/19/2025 Modified by BA HUY HOANG LE on 21/05/2025 | U4: Created by Microsoft Office User on 5/19/2025 Modified by BA HUY HOANG LE on 21/05/2025
B5: Changing Cells: | I5: Changing Cells: | P5: Changing Cells:
C6: ='1.b Model_Best estimates'!G5 -> Late cancellations percentage | D6: 0.15 | E6: 0.05 | F6: 0.15 | G6: 0.25 | J6: ='1.b Model_Best estimates'!G5 -> Late cancellations percentage | K6: 0.15 | L6: 0.05 | M6: 0.15 | N6: 0.25 | Q6: ='1.b Model_Best estimates'!G5 -> Late cancellations percentage | R6: 0.15 | S6: 0.05 | T6: 0.15 | U6: 0.25
B7: Result Cells: | I7: Result Cells: | P7: Result Cells:
C8: ='1.b Model_Best estimates'!B17 -> Total Daily Profit | D8: 211 | E8: 187 | F8: 211 | G8: 235 | J8: ='1.b Model_Best estimates'!B17 -> Total Daily Profit | K8: 735 | L8: 790 | M8: 735 | N8: 595 | Q8: ='1.b Model_Best estimates'!B17 -> Total Daily Profit | R8: -102 | S8: -5 | T8: -102 | U8: -199
B13: ='1.b Model_Best estimates'!G16 -> Room nightly rate ($) | C13: 120 | I13: ='1.b Model_Best estimates'!G16 -> Room nightly rate ($) | J13: 150 | P13: ='1.b Model_Best estimates'!G16 -> Room nightly rate ($) | Q13: 180
B14: Scenario Summary | I14: Scenario Summary | P14: Scenario Summary
D15: Current Values: | E15: Best Case | F15: Base Case | G15: Worst Case | K15: Current Values: | L15: Best Case | M15: Base Case | N15: Worst Case | R15: Current Values: | S15: Best Case | T15: Base Case | U15: Worst Case
B16: Changing Cells: | I16: Changing Cells: | P16: Changing Cells:
C17: ='1.b Model_Best estimates'!G5 -> Late cancellations percentage | D17: 0.15 | E17: 0.05 | F17: 0.15 | G17: 0.25 | J17: ='1.b Model_Best estimates'!G5 -> Late cancellations percentage | K17: 0.15 | L17: 0.05 | M17: 0.15 | N17: 0.25 | Q17: ='1.b Model_Best estimates'!G5 -> Late cancellations percentage | R17: 0.15 | S17: 0.05 | T17: 0.15 | U17: 0.25
B18: Result Cells: | I18: Result Cells: | P18: Result Cells:
C19: ='1.b Model_Best estimates'!B18 -> Sold Out: Yes/ No | D19: Yes | E19: Yes | F19: Yes | G19: Yes | J19: ='1.b Model_Best estimates'!B18 -> Sold Out: Yes/ No | K19: No | L19: Yes | M19: No | N19: No | Q19: ='1.b Model_Best estimates'!B18 -> Sold Out: Yes/ No | R19: No | S19: No | T19: No | U19: No

Sheet 2.a.3 Scenario for S input 3
B1: ='1.b Model_Best estimates'!G16 -> Room nightly rate ($) | C1: 120 | I1: ='1.b Model_Best estimates'!G16 -> Room nightly rate ($) | J1: 150 | P1: ='1.b Model_Best estimates'!G16 -> Room nightly rate ($) | Q1: 180
B2: Scenario Summary | I2: Scenario Summary | P2: Scenario Summary
D3: Current Values: | E3: Best Case | F3: Base Case | G3: Worst Case | K3: Current Values: | L3: Best Case | M3: Base Case | N3: Worst Case | R3: Current Values: | S3: Best Case | T3: Base Case | U3: Worst Case
E4: Created by Microsoft Office User on 5/19/2025 Modified by BA HUY HOANG LE on 21/05/2025 | F4: Created by Microsoft Office User on 5/19/2025 Modified by BA HUY HOANG LE on 21/05/2025 | G4: Created by Microsoft Office User on 5/19/2025 Modified by BA HUY HOANG LE on 21/05/2025 | L4: Created by Microsoft Office User on 5/19/2025 Modified by BA HUY HOANG LE on 21/05/2025 | M4: Created by Microsoft Office User on 5/19/2025 Modified by BA HUY HOANG LE on 21/05/2025 | N4: Created by Microsoft Office User on 5/19/2025 Modified by BA HUY HOANG LE on 21/05/2025 | S4: Created by Microsoft Office User on 5/19/2025 Modified by BA HUY HOANG LE on 21/05/2025 | T4: Created by Microsoft Office User on 5/19/2025 Modified by BA HUY HOANG LE on 21/05/2025 | U4: Created by Microsoft Office User on 5/19/2025 Modified by BA HUY HOANG LE on 21/05/2025
B5: Changing Cells: | I5: Changing Cells: | P5: Changing Cells:
C6: ='1.b Model_Best estimates'!G6 -> Walk-in arrivals | D6: 8 | E6: 8 | F6: 3 | G6: 1 | J6: ='1.b Model_Best estimates'!G6 -> Walk-in arrivals | K6: 8 | L6: 8 | M6: 3 | N6: 1 | Q6: ='1.b Model_Best estimates'!G6 -> Walk-in arrivals | R6: 8 | S6: 8 | T6: 3 | U6: 1
B7: Result Cells: | I7: Result Cells: | P7: Result Cells:
C8: ='1.b Model_Best estimates'!B17 -> Total Daily Profit | D8: 211 | E8: 211 | F8: 211 | G8: 211 | J8: ='1.b Model_Best estimates'!B17 -> Total Daily Profit | K8: 820 | L8: 820 | M8: 650 | N8: 480 | Q8: ='1.b Model_Best estimates'!B17 -> Total Daily Profit | R8: 703 | S8: 703 | T8: 128 | U8: -102
B13: ='1.b Model_Best estimates'!G16 -> Room nightly rate ($) | C13: 120 | I13: ='1.b Model_Best estimates'!G16 -> Room nightly rate ($) | J13: 150 | P13: ='1.b Model_Best estimates'!G16 -> Room nightly rate ($) | Q13: 180
B14: Scenario Summary | I14: Scenario Summary | P14: Scenario Summary
D15: Current Values: | E15: Best Case | F15: Base Case | G15: Worst Case | K15: Current Values: | L15: Best Case | M15: Base Case | N15: Worst Case | R15: Current Values: | S15: Best Case | T15: Base Case | U15: Worst Case
B16: Changing Cells: | I16: Changing Cells: | P16: Changing Cells:
C17: ='1.b Model_Best estimates'!G6 -> Walk-in arrivals | D17: 8 | E17: 8 | F17: 3 | G17: 1 | J17: ='1.b Model_Best estimates'!G6 -> Walk-in arrivals | K17: 8 | L17: 8 | M17: 3 | N17: 1 | Q17: ='1.b Model_Best estimates'!G6 -> Walk-in arrivals | R17: 8 | S17: 8 | T17: 3 | U17: 1
B18: Result Cells: | I18: Result Cells: | P18: Result Cells:
C19: ='1.b Model_Best estimates'!B18 -> Sold Out: Yes/ No | D19: Yes | E19: Yes | F19: Yes | G19: Yes | J19: ='1.b Model_Best estimates'!B18 -> Sold Out: Yes/ No | K19: Yes | L19: Yes | M19: No | N19: No | Q19: ='1.b Model_Best estimates'!B18 -> Sold Out: Yes/ No | R19: No | S19: No | T19: No | U19: No

Sheet 2.a.4 Scenario for S input  4
B1: ='1.b Model_Best estimates'!G16 -> Room nightly rate ($) | C1: 120 | I1: ='1.b Model_Best estimates'!G16 -> Room nightly rate ($) | J1: 150 | P1: ='1.b Model_Best estimates'!G16 -> Room nightly rate ($) | Q1: 180
B2: Scenario Summary | I2: Scenario Summary | P2: Scenario Summary
D3: Current Values: | E3: Best Case | F3: Base Case | G3: Worst Case | K3: Current Values: | L3: Best Case | M3: Base Case | N3: Worst Case | R3: Current Values: | S3: Best Case | T3: Base Case | U3: Worst Case
E4: Created by Microsoft Office User on 5/19/2025 Modified by BA HUY HOANG LE on 21/05/2025 | F4: Created by Microsoft Office User on 5/19/2025 Modified by BA HUY HOANG LE on 21/05/2025 | G4: Created by Microsoft Office User on 5/19/2025 Modified by BA HUY HOANG LE on 21/05/2025 | L4: Created by Microsoft Office User on 5/19/2025 Modified by BA HUY HOANG LE on 21/05/2025 | M4: Created by Microsoft Office User on 5/19/2025 Modified by BA HUY HOANG LE on 21/05/2025 | N4: Created by Microsoft Office User on 5/19/2025 Modified by BA HUY HOANG LE on 21/05/2025 | S4: Created by Microsoft Office User on 5/19/2025 Modified by BA HUY HOANG LE on 21/05/2025 | T4: Created by Microsoft Office User on 5/19/2025 Modified by BA HUY HOANG LE on 21/05/2025 | U4: Created by Microsoft Office User on 5/19/2025 Modified by BA HUY HOANG LE on 21/05/2025
B5: Changing Cells: | I5: Changing Cells: | P5: Changing Cells:
C6: ='1.b Model_Best estimates'!G7 -> Miscellaneuous daily expenses | D6: 300 | E6: 100 | F6: 300 | G6: 600 | J6: ='1.b Model_Best estimates'!G7 -> Miscellaneuous daily expenses | K6: 300 | L6: 100 | M6: 300 | N6: 600 | Q6: ='1.b Model_Best estimates'!G7 -> Miscellaneuous daily expenses | R6: 300 | S6: 100 | T6: 300 | U6: 600
B7: Result Cells: | I7: Result Cells: | P7: Result Cells:
C8: ='1.b Model_Best estimates'!B17 -> Total Daily Profit | D8: 211 | E8: 411 | F8: 211 | G8: -89 | J8: ='1.b Model_Best estimates'!B17 -> Total Daily Profit | K8: 650 | L8: 850 | M8: 650 | N8: 350 | Q8: ='1.b Model_Best estimates'!B17 -> Total Daily Profit | R8: 128 | S8: 328 | T8: 128 | U8: -172
B13: ='1.b Model_Best estimates'!G16 -> Room nightly rate ($) | C13: 120 | I13: ='1.b Model_Best estimates'!G16 -> Room nightly rate ($) | J13: 150 | P13: ='1.b Model_Best estimates'!G16 -> Room nightly rate ($) | Q13: 180
B14: Scenario Summary | I14: Scenario Summary | P14: Scenario Summary
D15: Current Values: | E15: Best Case | F15: Base Case | G15: Worst Case | K15: Current Values: | L15: Best Case | M15: Base Case | N15: Worst Case | R15: Current Values: | S15: Best Case | T15: Base Case | U15: Worst Case
B16: Changing Cells: | I16: Changing Cells: | P16: Changing Cells:
C17: ='1.b Model_Best estimates'!G7 -> Miscellaneuous daily expenses | D17: 300 | E17: 100 | F17: 300 | G17: 600 | J17: ='1.b Model_Best estimates'!G7 -> Miscellaneuous daily expenses | K17: 300 | L17: 100 | M17: 300 | N17: 600 | Q17: ='1.b Model_Best estimates'!G7 -> Miscellaneuous daily expenses | R17: 300 | S17: 100 | T17: 300 | U17: 600
B18: Result Cells: | I18: Result Cells: | P18: Result Cells:
C19: ='1.b Model_Best estimates'!B18 -> Sold Out: Yes/ No | D19: Yes | E19: Yes | F19: Yes | G19: Yes | J19: ='1.b Model_Best estimates'!B18 -> Sold Out: Yes/ No | K19: No | L19: No | M19: No | N19: No | Q19: ='1.b Model_Best estimates'!B18 -> Sold Out: Yes/ No | R19: No | S19: No | T19: No | U19: No

Sheet 2.bSummary of Scenario analysis
B1: Nightly Room Rate $120 | J1: Nightly Room Rate $150 | R1: Nightlt Room Rate $180
B2: Scenarios | C2: Best | D2: Base | E2: Worst | J2: =B2 -> Scenarios | K2: =C2 -> Best | L2: =D2 -> Base | M2: =E2 -> Worst | R2: =B2 -> Scenarios | S2: =C2 -> Best | T2: =D2 -> Base | U2: =E2 -> Worst
A4: changing cell | B4: ='1.b Model_Best estimates'!G4 -> Daily online reservations | C4: ='2.a.1 Scenario for S input 1'!E6 -> 22 | D4: ='2.a.1 Scenario for S input 1'!F6 -> 18 | E4: ='2.a.1 Scenario for S input 1'!G6 -> 7 | I4: changing cell | J4: ='1.b Model_Best estimates'!G4 -> Daily online reservations | K4: ='2.a.1 Scenario for S input 1'!L6 -> 22 | L4: ='2.a.1 Scenario for S input 1'!M6 -> 18 | M4: ='2.a.1 Scenario for S input 1'!N6 -> 7 | Q4: changing cell | R4: ='1.b Model_Best estimates'!G4 -> Daily online reservations | S4: ='2.a.1 Scenario for S input 1'!S6 -> 22 | T4: ='2.a.1 Scenario for S input 1'!T6 -> 18 | U4: ='2.a.1 Scenario for S input 1'!U6 -> 7
A5: Output result | B5: ='1.b Model_Best estimates'!B17 -> Total Daily Profit | C5: ='2.a.1 Scenario for S input 1'!E8 -> 211 | D5: ='2.a.1 Scenario for S input 1'!F8 -> 211 | E5: ='2.a.1 Scenario for S input 1'!G8 -> -143 | I5: Output result | J5: ='1.b Model_Best estimates'!B17 -> Total Daily Profit | K5: ='2.a.1 Scenario for S input 1'!L8 -> 820 | L5: ='2.a.1 Scenario for S input 1'!M8 -> 735 | M5: ='2.a.1 Scenario for S input 1'!N8 -> -60 | Q5: Output result | R5: ='1.b Model_Best estimates'!B17 -> Total Daily Profit | S5: ='2.a.1 Scenario for S input 1'!S8 -> 1429 | T5: ='2.a.1 Scenario for S input 1'!T8 -> 969 | U5: ='2.a.1 Scenario for S input 1'!U8 -> -102
B6: ='1.b Model_Best estimates'!B18 -> Sold Out: Yes/ No | C6: ='2.a.1 Scenario for S input 1'!E19 -> Yes | D6: ='2.a.1 Scenario for S input 1'!F19 -> Yes | E6: ='2.a.1 Scenario for S input 1'!G19 -> No | J6: ='1.b Model_Best estimates'!B18 -> Sold Out: Yes/ No | K6: ='2.a.1 Scenario for S input 1'!L19 -> Yes | L6: ='2.a.1 Scenario for S input 1'!M19 -> No | M6: ='2.a.1 Scenario for S input 1'!N19 -> No | R6: ='1.b Model_Best estimates'!B18 -> Sold Out: Yes/ No | S6: ='2.a.1 Scenario for S input 1'!S19 -> Yes | T6: ='2.a.1 Scenario for S input 1'!T19 -> No | U6: ='2.a.1 Scenario for S input 1'!U19 -> No
A8: changing cell | B8: ='1.b Model_Best estimates'!G5 -> Late cancellations percentage | C8: ='2.a.2 Scenario for S input 2'!E6 -> 0.05 | D8: ='2.a.2 Scenario for S input 2'!F6 -> 0.15 | E8: ='2.a.2 Scenario for S input 2'!G6 -> 0.25 | I8: changing cell | J8: ='1.b Model_Best estimates'!G5 -> Late cancellations percentage | K8: ='2.a.2 Scenario for S input 2'!L6 -> 0.05 | L8: ='2.a.2 Scenario for S input 2'!M6 -> 0.15 | M8: ='2.a.2 Scenario for S input 2'!N6 -> 0.25 | Q8: changing cell | R8: ='1.b Model_Best estimates'!G5 -> Late cancellations percentage | S8: ='2.a.2 Scenario for S input 2'!S6 -> 0.05 | T8: ='2.a.2 Scenario for S input 2'!T6 -> 0.15 | U8: ='2.a.2 Scenario for S input 2'!U6 -> 0.25
A9: Output result | B9: ='1.b Model_Best estimates'!B17 -> Total Daily Profit | C9: ='2.a.2 Scenario for S input 2'!E8 -> 187 | D9: ='2.a.2 Scenario for S input 2'!F8 -> 211 | E9: ='2.a.2 Scenario for S input 2'!G8 -> 235 | I9: Output result | J9: ='1.b Model_Best estimates'!B17 -> Total Daily Profit | K9: ='2.a.2 Scenario for S input 2'!L8 -> 790 | L9: ='2.a.2 Scenario for S input 2'!M8 -> 735 | M9: ='2.a.2 Scenario for S input 2'!N8 -> 595 | Q9: Output result | R9: ='1.b Model_Best estimates'!B17 -> Total Daily Profit | S9: ='2.a.2 Scenario for S input 2'!S8 -> -5 | T9: ='2.a.2 Scenario for S input 2'!T8 -> -102 | U9: ='2.a.2 Scenario for S input 2'!U8 -> -199
B10: ='1.b Model_Best estimates'!B18 -> Sold Out: Yes/ No | C10: ='2.a.2 Scenario for S input 2'!E19 -> Yes | D10: ='2.a.2 Scenario for S input 2'!F19 -> Yes | E10: ='2.a.2 Scenario for S input 2'!G19 -> Yes | J10: ='1.b Model_Best estimates'!B18 -> Sold Out: Yes/ No | K10: ='2.a.2 Scenario for S input 2'!L19 -> Yes | L10: ='2.a.2 Scenario for S input 2'!M19 -> No | M10: ='2.a.2 Scenario for S input 2'!N19 -> No | R10: ='1.b Model_Best estimates'!B18 -> Sold Out: Yes/ No | S10: ='2.a.2 Scenario for S input 2'!S19 -> No | T10: ='2.a.2 Scenario for S input 2'!T19 -> No | U10: ='2.a.2 Scenario for S input 2'!U19 -> No
A12: changing cell | B12: ='1.b Model_Best estimates'!G6 -> Walk-in arrivals | C12: ='2.a.3 Scenario for S input 3'!L6 -> 8 | D12: ='2.a.3 Scenario for S input 3'!M6 -> 3 | E12: ='2.a.3 Scenario for S input 3'!N6 -> 1 | I12: changing cell | J12: ='1.b Model_Best estimates'!G6 -> Walk-in arrivals | K12: ='2.a.3 Scenario for S input 3'!L6 -> 8 | L12: ='2.a.3 Scenario for S input 3'!M6 -> 3 | M12: ='2.a.3 Scenario for S input 3'!N6 -> 1 | Q12: changing cell | R12: ='1.b Model_Best estimates'!G6 -> Walk-in arrivals | S12: ='2.a.3 Scenario for S input 3'!S6 -> 8 | T12: ='2.a.3 Scenario for S input 3'!T6 -> 3 | U12: ='2.a.3 Scenario for S input 3'!U6 -> 1
A13: Output result | B13: ='1.b Model_Best estimates'!B17 -> Total Daily Profit | C13: ='2.a.3 Scenario for S input 3'!E8 -> 211 | D13: ='2.a.3 Scenario for S input 3'!F8 -> 211 | E13: ='2.a.3 Scenario for S input 3'!G8 -> 211 | I13: Output result | J13: ='1.b Model_Best estimates'!B17 -> Total Daily Profit | K13: ='2.a.3 Scenario for S input 3'!L8 -> 820 | L13: ='2.a.3 Scenario for S input 3'!M8 -> 650 | M13: ='2.a.3 Scenario for S input 3'!N8 -> 480 | Q13: Output result | R13: ='1.b Model_Best estimates'!B17 -> Total Daily Profit | S13: ='2.a.3 Scenario for S input 3'!S8 -> 703 | T13: ='2.a.3 Scenario for S input 3'!T8 -> 128 | U13: ='2.a.3 Scenario for S input 3'!U8 -> -102
B14: ='1.b Model_Best estimates'!B18 -> Sold Out: Yes/ No | C14: ='2.a.3 Scenario for S input 3'!E19 -> Yes | D14: ='2.a.3 Scenario for S input 3'!F19 -> Yes | E14: ='2.a.3 Scenario for S input 3'!G19 -> Yes | J14: ='1.b Model_Best estimates'!B18 -> Sold Out: Yes/ No | K14: ='2.a.3 Scenario for S input 3'!L19 -> Yes | L14: ='2.a.3 Scenario for S input 3'!M19 -> No | M14: ='2.a.3 Scenario for S input 3'!N19 -> No | R14: ='1.b Model_Best estimates'!B18 -> Sold Out: Yes/ No | S14: ='2.a.3 Scenario for S input 3'!S19 -> No | T14: ='2.a.3 Scenario for S input 3'!T19 -> No | U14: ='2.a.3 Scenario for S input 3'!U19 -> No
A16: changing cell | B16: ='2.a.4 Scenario for S input 4'!J6 -> Miscellaneuous daily expenses | C16: ='2.a.4 Scenario for S input 4'!L6 -> 100 | D16: ='2.a.4 Scenario for S input 4'!M6 -> 300 | E16: ='2.a.4 Scenario for S input 4'!N6 -> 600 | I16: changing cell | J16: ='2.a.4 Scenario for S input 4'!J6 -> Miscellaneuous daily expenses | K16: ='2.a.4 Scenario for S input 4'!L6 -> 100 | L16: ='2.a.4 Scenario for S input 4'!M6 -> 300 | M16: ='2.a.4 Scenario for S input 4'!N6 -> 600 | Q16: changing cell | R16: ='2.a.4 Scenario for S input 4'!J6 -> Miscellaneuous daily expenses | S16: ='2.a.4 Scenario for S input 4'!S17 -> 100 | T16: ='2.a.4 Scenario for S input 4'!T17 -> 300 | U16: ='2.a.4 Scenario for S input 4'!U17 -> 600
A17: Output result | B17: ='1.b Model_Best estimates'!B17 -> Total Daily Profit | C17: ='2.a.4 Scenario for S input 4'!E8 -> 411 | D17: ='2.a.4 Scenario for S input 4'!F8 -> 211 | E17: ='2.a.4 Scenario for S input 4'!G8 -> -89 | I17: Output result | J17: ='1.b Model_Best estimates'!B17 -> Total Daily Profit | K17: ='2.a.4 Scenario for S input 4'!L8 -> 850 | L17: ='2.a.4 Scenario for S input 4'!M8 -> 650 | M17: ='2.a.4 Scenario for S input 4'!N8 -> 350 | Q17: Output result | R17: ='1.b Model_Best estimates'!B17 -> Total Daily Profit | S17: {='2.a.4 Scenario for S input 4'!S8:U8} -> 328 | T17: 128 | U17: -172
B18: ='1.b Model_Best estimates'!B18 -> Sold Out: Yes/ No | C18: ='2.a.4 Scenario for S input 4'!E19 -> Yes | D18: ='2.a.4 Scenario for S input 4'!F19 -> Yes | E18: ='2.a.4 Scenario for S input 4'!G19 -> Yes | J18: ='1.b Model_Best estimates'!B18 -> Sold Out: Yes/ No | K18: ='2.a.4 Scenario for S input 4'!L19 -> No | L18: ='2.a.4 Scenario for S input 4'!M19 -> No | M18: ='2.a.4 Scenario for S input 4'!N19 -> No | R18: ='1.b Model_Best estimates'!B18 -> Sold Out: Yes/ No | S18: ='2.a.4 Scenario for S input 4'!S19 -> No | T18: ='2.a.4 Scenario for S input 4'!T19 -> No | U18: ='2.a.4 Scenario for S input 4'!U19 -> No

Sheet 3.a Observed Data
A1: S Input 1 - Daily Online Reservation | K1: S Input 2 - Late Cancellation Percentage | T1: S Input 3 - Walk-in Arrivals | AH1: S Input 4 - Miscellaneous Daily Expenses
A2: Dates when room rate $120 | D2: Dates when room rate $150 | G2: Dates when room rate $180
A3: Date | B3: ='1.a Manager''s Page'!B4 -> Daily online reservations | D3: Date | E3: ='1.a Manager''s Page'!B4 -> Daily online reservations | G3: Date | H3: ='1.a Manager''s Page'!B4 -> Daily online reservations | L3: Date | M3: ='1.a Manager''s Page'!B5 -> Late cancellations percentage | O3: ='1.a Manager''s Page'!B5 -> Late cancellations percentage | P3: Probability of Late cancellation percentage | Q3: Probability of Late cancellation percentage (%) | U3: Date | V3: ='1.a Manager''s Page'!B6 -> Walk-in arrivals | X3: ='1.a Manager''s Page'!B6 -> Walk-in arrivals | Y3: Count of walk-in arrivals | Z3: Count of walk-in arrivals (%)
A4: 44900 | B4: 19.760588 | D4: 44896 | E4: 19 | G4: 44897 | H4: 7 | L4: 44896 | M4: 0.1 | O4: 0.05 | P4: =COUNTIF($L$4:$M$274,O4) -> 73 | Q4: =P4/$P$9 -> 0.26937269 | U4: 44896 | V4: 3 | X4: 0 | Y4: =COUNTIF($U$4:$V$274,X4) -> 15 | Z4: =Y4/$Y$15 -> 0.055350554
A5: 44901 | B5: 19.500679 | D5: 44899 | E5: 18 | G5: 44898 | H5: 8 | L5: 44897 | M5: 0.25 | O5: 0.1 | P5: =COUNTIF($L$4:$M$274,O5) -> 52 | Q5: =P5/$P$9 -> 0.19188192 | U5: 44897 | V5: 10 | X5: 1 | Y5: =COUNTIF($U$4:$V$274,X5) -> 45 | Z5: =Y5/$Y$15 -> 0.16605166
A6: 44902 | B6: 21.282195 | D6: 44904 | E6: 20 | G6: 44903 | H6: 9 | L6: 44898 | M6: 0.15 | O6: 0.15 | P6: =COUNTIF($L$4:$M$274,O6) -> 78 | Q6: =P6/$P$9 -> 0.28782288 | U6: 44898 | V6: 6 | X6: 2 | Y6: =COUNTIF($U$4:$V$274,X6) -> 27 | Z6: =Y6/$Y$15 -> 0.099630996
A7: 44906 | B7: 22.557497 | D7: 44913 | E7: 15 | G7: 44905 | H7: 6 | L7: 44899 | M7: 0.15 | O7: 0.2 | P7: =COUNTIF($L$4:$M$274,O7) -> 40 | Q7: =P7/$P$9 -> 0.14760148 | U7: 44899 | V7: 3 | X7: 3 | Y7: =COUNTIF($U$4:$V$274,X7) -> 72 | Z7: =Y7/$Y$15 -> 0.26568266
A8: 44909 | B8: 23.993725 | D8: 44914 | E8: 16 | G8: 44907 | H8: 7 | L8: 44900 | M8: 0.05 | O8: 0.25 | P8: =COUNTIF($L$4:$M$274,O8) -> 28 | Q8: =P8/$P$9 -> 0.10332103 | U8: 44900 | V8: 1 | X8: 4 | Y8: =COUNTIF($U$4:$V$274,X8) -> 24 | Z8: =Y8/$Y$15 -> 0.088560886
A9: 44910 | B9: 27.69205 | D9: 44916 | E9: 18 | G9: 44908 | H9: 6 | L9: 44901 | M9: 0.05 | P9: =COUNT(M4:M274) -> 271 | Q9: =SUM(Q4:Q8) -> 1 | R9: Total | U9: 44901 | V9: 1 | X9: 5 | Y9: =COUNTIF($U$4:$V$274,X9) -> 6 | Z9: =Y9/$Y$15 -> 0.022140221
A10: 44911 | B10: 18.620041 | D10: 44919 | E10: 15 | G10: 44921 | H10: 7 | L10: 44902 | M10: 0.05 | U10: 44902 | V10: 1 | X10: 6 | Y10: =COUNTIF($U$4:$V$274,X10) -> 14 | Z10: =Y10/$Y$15 -> 0.051660517
A11: 44912 | B11: 21.791309 | D11: 44920 | E11: 19 | G11: 44929 | H11: 6 | L11: 44903 | M11: 0.2 | U11: 44903 | V11: 8 | X11: 7 | Y11: =COUNTIF($U$4:$V$274,X11) -> 10 | Z11: =Y11/$Y$15 -> 0.036900369
A12: 44915 | B12: 19.75144 | D12: 44923 | E12: 16 | G12: 44930 | H12: 8 | L12: 44904 | M12: 0.15 | U12: 44904 | V12: 4 | X12: 8 | Y12: =COUNTIF($U$4:$V$274,X12) -> 30 | Z12: =Y12/$Y$15 -> 0.11070111
A13: 44917 | B13: 22.654604 | D13: 44924 | E13: 16 | G13: 44931 | H13: 8 | L13: 44905 | M13: 0.15 | U13: 44905 | V13: 6 | X13: 9 | Y13: =COUNTIF($U$4:$V$274,X13) -> 15 | Z13: =Y13/$Y$15 -> 0.055350554
A14: 44918 | B14: 27.770156 | D14: 44926 | E14: 20 | G14: 44934 | H14: 9 | L14: 44906 | M14: 0.05 | U14: 44906 | V14: 0 | X14: 10 | Y14: =COUNTIF($U$4:$V$274,X14) -> 13 | Z14: =Y14/$Y$15 -> 0.04797048
A15: 44922 | B15: 21.885614 | D15: 44935 | E15: 21 | G15: 44939 | H15: 7 | L15: 44907 | M15: 0.25 | U15: 44907 | V15: 10 | Y15: =SUM(Y4:Y14) -> 271 | Z15: =SUM(Z4:Z14) -> 1 | AA15: Total
A16: 44925 | B16: 21.281992 | D16: 44937 | E16: 16 | G16: 44946 | H16: 10 | L16: 44908 | M16: 0.2 | U16: 44908 | V16: 8
A17: 44927 | B17: 27.679355 | D17: 44941 | E17: 11 | G17: 44947 | H17: 6 | L17: 44909 | M17: 0.05 | U17: 44909 | V17: 2
A18: 44928 | B18: 24.177148 | D18: 44943 | E18: 14 | G18: 44948 | H18: 7 | L18: 44910 | M18: 0.05 | U18: 44910 | V18: 1
A19: 44932 | B19: 24.357936 | D19: 44944 | E19: 13 | G19: 44949 | H19: 7 | L19: 44911 | M19: 0.05 | U19: 44911 | V19: 1
A20: 44933 | B20: 23.995645 | D20: 44950 | E20: 21 | G20: 44951 | H20: 5 | L20: 44912 | M20: 0.1 | U20: 44912 | V20: 3
A21: 44936 | B21: 24.719042 | D21: 44956 | E21: 15 | G21: 44958 | H21: 7 | L21: 44913 | M21: 0.15 | U21: 44913 | V21: 3
A22: 44938 | B22: 18.39778 | D22: 44959 | E22: 17 | G22: 44963 | H22: 9 | L22: 44914 | M22: 0.1 | U22: 44914 | V22: 3
A23: 44940 | B23: 24.268159 | D23: 44961 | E23: 18 | G23: 44965 | H23: 6 | L23: 44915 | M23: 0.1 | U23: 44915 | V23: 2
A24: 44942 | B24: 23.400737 | D24: 44974 | E24: 17 | G24: 44966 | H24: 8 | L24: 44916 | M24: 0.15 | U24: 44916 | V24: 4
A25: 44945 | B25: 24.240217 | D25: 44977 | E25: 15 | G25: 44969 | H25: 11 | L25: 44917 | M25: 0.05 | U25: 44917 | V25: 1
A26: 44952 | B26: 19.565117 | D26: 44978 | E26: 16 | G26: 44970 | H26: 6 | L26: 44918 | M26: 0.1 | U26: 44918 | V26: 2
A27: 44953 | B27: 24.933792 | D27: 44983 | E27: 16 | G27: 44971 | H27: 9 | L27: 44919 | M27: 0.1 | U27: 44919 | V27: 3
... A85: 45654 | B85: 21.873239 | D85: 45714 | E85: 21 | G85: 45702 | H85: 8 | L85: 44977 | M85: 0.15 | U85: 44977 | V85: 4
A86: 45655 | B86: 23.68445 | G86: 45703 | H86: 6 | L86: 44978 | M86: 0.1 | U86: 44978 | V86: 3
A87: 45659 | B87: 21.224431 | G87: 45707 | H87: 4 | L87: 44979 | M87: 0.05 | U87: 44979 | V87: 1
A88: 45661 | B88: 22.375614 | G88: 45710 | H88: 8 | L88: 44980 | M88: 0.1 | U88: 44980 | V88: 3
A89: 45662 | B89: 19.548988 | G89: 45711 | H89: 8 | L89: 44981 | M89: 0.1 | U89: 44981 | V89: 3
A90: 45668 | B90: 17.979875 | G90: 45712 | H90: 6 | L90: 44982 | M90: 0.15 | U90: 44982 | V90: 6
A91: 45670 | B91: 19.986951 | G91: 45713 | H91: 6 | L91: 44983 | M91: 0.15 | U91: 44983 | V91: 4
A92: 45671 | B92: 17.367662 | G92: 45716 | H92: 5 | L92: 44984 | M92: 0.2 | U92: 44984 | V92: 8
A93: 45680 | B93: 24.411205 | L93: 44985 | M93: 0.15 | U93: 44985 | V93: 3
A94: 45682 | B94: 17.542631 | L94: 45261 | M94: 0.05 | U94: 45261 | V94: 1
A95: 45683 | B95: 20.992517 | L95: 45262 | M95: 0.15 | U95: 45262 | V95: 6
A96: 45685 | B96: 26.138578 | L96: 45263 | M96: 0.2 | U96: 45263 | V96: 7
A97: 45690 | B97: 20.129942 | L97: 45264 | M97: 0.15 | U97: 45264 | V97: 3
A98: 45696 | B98: 16.294634 | L98: 45265 | M98: 0.2 | U98: 45265 | V98: 7
A99: 45699 | B99: 14.005029 | L99: 45266 | M99: 0.15 | U99: 45266 | V99: 3
A100: 45700 | B100: 23.580405 | L100: 45267 | M100: 0.15 | U100: 45267 | V100: 3
A101: 45705 | B101: 23.485035 | L101: 45268 | M101: 0.1 | U101: 45268 | V101: 3
A102: 45708 | B102: 23.755747 | L102: 45269 | M102: 0.05 | U102: 45269 | V102: 0
A103: 45715 | B103: 18.096402 | L103: 45270 | M103: 0.05 | U103: 45270 | V103: 1
L104: 45271 | M104: 0.05 | U104: 45271 | V104: 0
L105: 45272 | M105: 0.15 | U105: 45272 | V105: 4
L106: 45273 | M106: 0.1 | U106: 45273 | V106: 3
L107: 45274 | M107: 0.15 | U107: 45274 | V107: 3
L108: 45275 | M108: 0.25 | U108: 45275 | V108: 9
L109: 45276 | M109: 0.05 | U109: 45276 | V109: 2
L110: 45277 | M110: 0.1 | U110: 45277 | V110: 3
L111: 45278 | M111: 0.2 | U111: 45278 | V111: 7
L112: 45279 | M112: 0.05 | U112: 45279 | V112: 2
L113: 45280 | M113: 0.05 | U113: 45280 | V113: 1
L114: 45281 | M114: 0.1 | U114: 45281 | V114: 2
L115: 45282 | M115: 0.05 | U115: 45282 | V115: 1
... L274: 45716 | M274: 0.2 | U274: 45716 | V274: 8

Sheet 3.b Probability Distributions
A1: S Input 1 - Daily Online Reservation | H1: S Input 2 - Late Cancellation Percentage | S1: S Input 3 - Walk-in Arrivals | AC1: S Input 4 - Miscellaneous Daily Expenses
F3: =IF(#REF!>(#REF!-#REF!)/(#REF!-#REF!),#REF!-SQRT((1-#REF!)*(#REF!-#REF!)*(#REF!-#REF!)),#REF!+SQRT(#REF!*(#REF!-#REF!)*(#REF!-#REF!))) -> #REF!
F4: =IF(#REF!>(#REF!-#REF!)/(#REF!-#REF!),#REF!-SQRT((1-#REF!)*(#REF!-#REF!)*(#REF!-#REF!)),#REF!+SQRT(#REF!*(#REF!-#REF!)*(#REF!-#REF!))) -> #REF! | J4: Late Cancellation Portions | K4: Probability | L4: Cumulative distribution | N4: Lower limit | O4: Upper limit | P4: ='1.a Manager''s Page'!B5 -> Late cancellations percentage | T4: No. of Arrivals | U4: Probability | V4: Cumulative | X4: Lower limit | Y4: Upper limit | Z4: No. of arrivals | AG4: Lower limit | AH4: Upper limit
F5: =IF(#REF!>(#REF!-#REF!)/(#REF!-#REF!),#REF!-SQRT((1-#REF!)*(#REF!-#REF!)*(#REF!-#REF!)),#REF!+SQRT(#REF!*(#REF!-#REF!)*(#REF!-#REF!))) -> #REF! | V5: distribution | X5: Lower limit | Y5: Upper Limit
F6: =IF(#REF!>(#REF!-#REF!)/(#REF!-#REF!),#REF!-SQRT((1-#REF!)*(#REF!-#REF!)*(#REF!-#REF!)),#REF!+SQRT(#REF!*(#REF!-#REF!)*(#REF!-#REF!))) -> #REF! | J6: 0.05 | K6: ='3.a Observed Data'!Q4 -> 0.26937269 | L6: =K6 -> 0.26937269 | N6: 0 | O6: =L6 -> 0.26937269 | P6: =J6 -> 0.05 | T6: 0 | U6: ='3.a Observed Data'!Z4 -> 0.055350554 | V6: =U6 -> 0.055350554 | X6: 0 | Y6: =V6 -> 0.055350554 | Z6: 0 | AF6: Uniform | AG6: 100 | AH6: 600
F7: =IF(#REF!>(#REF!-#REF!)/(#REF!-#REF!),#REF!-SQRT((1-#REF!)*(#REF!-#REF!)*(#REF!-#REF!)),#REF!+SQRT(#REF!*(#REF!-#REF!)*(#REF!-#REF!))) -> #REF! | J7: 0.1 | K7: ='3.a Observed Data'!Q5 -> 0.19188192 | L7: =L6+K7 -> 0.46125461 | N7: =O6 -> 0.26937269 | O7: =L7 -> 0.46125461 | P7: =J7 -> 0.1 | T7: 1 | U7: ='3.a Observed Data'!Z5 -> 0.16605166 | V7: =V6+U7 -> 0.22140221 | X7: =Y6 -> 0.055350554 | Y7: =V7 -> 0.22140221 | Z7: 1
F8: =IF(#REF!>(#REF!-#REF!)/(#REF!-#REF!),#REF!-SQRT((1-#REF!)*(#REF!-#REF!)*(#REF!-#REF!)),#REF!+SQRT(#REF!*(#REF!-#REF!)*(#REF!-#REF!))) -> #REF! | J8: 0.15 | K8: ='3.a Observed Data'!Q6 -> 0.28782288 | L8: =L7+K8 -> 0.74907749 | N8: =O7 -> 0.46125461 | O8: =L8 -> 0.74907749 | P8: =J8 -> 0.15 | T8: 2 | U8: ='3.a Observed Data'!Z6 -> 0.099630996 | V8: =V7+U8 -> 0.32103321 | X8: =Y7 -> 0.22140221 | Y8: =V8 -> 0.32103321 | Z8: 2
F9: =IF(#REF!>(#REF!-#REF!)/(#REF!-#REF!),#REF!-SQRT((1-#REF!)*(#REF!-#REF!)*(#REF!-#REF!)),#REF!+SQRT(#REF!*(#REF!-#REF!)*(#REF!-#REF!))) -> #REF! | J9: 0.2 | K9: ='3.a Observed Data'!Q7 -> 0.14760148 | L9: =L8+K9 -> 0.89667897 | N9: =O8 -> 0.74907749 | O9: =L9 -> 0.89667897 | P9: =J9 -> 0.2 | T9: 3 | U9: ='3.a Observed Data'!Z7 -> 0.26568266 | V9: =V8+U9 -> 0.58671587 | X9: =Y8 -> 0.32103321 | Y9: =V9 -> 0.58671587 | Z9: 3 | AD9: Miscellaneous Daily Expenses | AG9: =RAND() -> 0.70745741 | AH9: =$AG$6+($AH$6-$AG$6)*$AG$9 -> 453.7287
C10: Mean | D10: Standard deviation | F10: =IF(#REF!>(#REF!-#REF!)/(#REF!-#REF!),#REF!-SQRT((1-#REF!)*(#REF!-#REF!)*(#REF!-#REF!)),#REF!+SQRT(#REF!*(#REF!-#REF!)*(#REF!-#REF!))) -> #REF! | J10: 0.25 | K10: ='3.a Observed Data'!Q8 -> 0.10332103 | L10: =L9+K10 -> 1 | N10: =O9 -> 0.89667897 | O10: =L10 -> 1 | P10: =J10 -> 0.25 | T10: 4 | U10: ='3.a Observed Data'!Z8 -> 0.088560886 | V10: =V9+U10 -> 0.67527675 | X10: =Y9 -> 0.58671587 | Y10: =V10 -> 0.67527675 | Z10: 4
B11: Price at $120 | C11: =AVERAGE('3.a Observed Data'!B4:B103) -> 22.269787 | D11: =C11*0.17 -> 3.7858638 | F11: =IF(#REF!>(#REF!-#REF!)/(#REF!-#REF!),#REF!-SQRT((1-#REF!)*(#REF!-#REF!)*(#REF!-#REF!)),#REF!+SQRT(#REF!*(#REF!-#REF!)*(#REF!-#REF!))) -> #REF! | T11: 5 | U11: ='3.a Observed Data'!Z9 -> 0.022140221 | V11: =V10+U11 -> 0.69741697 | X11: =Y10 -> 0.67527675 | Y11: =V11 -> 0.69741697 | Z11: 5
B12: Price at $150 | C12: =AVERAGE('3.a Observed Data'!E4:E85) -> 17.97561 | D12: =C12*0.17 -> 3.0558537 | F12: =IF(#REF!>(#REF!-#REF!)/(#REF!-#REF!),#REF!-SQRT((1-#REF!)*(#REF!-#REF!)*(#REF!-#REF!)),#REF!+SQRT(#REF!*(#REF!-#REF!)*(#REF!-#REF!))) -> #REF! | T12: 6 | U12: ='3.a Observed Data'!Z10 -> 0.051660517 | V12: =V11+U12 -> 0.74907749 | X12: =Y11 -> 0.69741697 | Y12: =V12 -> 0.74907749 | Z12: 6
B13: Price at $180 | C13: =AVERAGE('3.a Observed Data'!H4:H92) -> 6.9662921 | D13: =C13*0.17 -> 1.1842697 | F13: =IF(#REF!>(#REF!-#REF!)/(#REF!-#REF!),#REF!-SQRT((1-#REF!)*(#REF!-#REF!)*(#REF!-#REF!)),#REF!+SQRT(#REF!*(#REF!-#REF!)*(#REF!-#REF!))) -> #REF! | T13: 7 | U13: ='3.a Observed Data'!Z11 -> 0.036900369 | V13: =V12+U13 -> 0.78597786 | X13: =Y12 -> 0.74907749 | Y13: =V13 -> 0.78597786 | Z13: 7
F14: =IF(#REF!>(#REF!-#REF!)/(#REF!-#REF!),#REF!-SQRT((1-#REF!)*(#REF!-#REF!)*(#REF!-#REF!)),#REF!+SQRT(#REF!*(#REF!-#REF!)*(#REF!-#REF!))) -> #REF! | T14: 8 | U14: ='3.a Observed Data'!Z12 -> 0.11070111 | V14: =V13+U14 -> 0.89667897 | X14: =Y13 -> 0.78597786 | Y14: =V14 -> 0.89667897 | Z14: 8
B15: Daily online reservation when price $120 | C15: =RAND() -> 0.83057782 | D15: =MAX(0,_xlfn.NORM.INV($C$15,$C$11,$D$11)) -> 25.890781 | F15: =IF(#REF!>(#REF!-#REF!)/(#REF!-#REF!),#REF!-SQRT((1-#REF!)*(#REF!-#REF!)*(#REF!-#REF!)),#REF!+SQRT(#REF!*(#REF!-#REF!)*(#REF!-#REF!))) -> #REF! | T15: 9 | U15: ='3.a Observed Data'!Z13 -> 0.055350554 | V15: =V14+U15 -> 0.95202952 | X15: =Y14 -> 0.89667897 | Y15: =V15 -> 0.95202952 | Z15: 9
B16: Daily online reservation when price $150 | C16: =RAND() -> 0.46332073 | D16: =MAX(0,_xlfn.NORM.INV($C$16,$C$12,$D$12)) -> 17.694254 | F16: =IF(#REF!>(#REF!-#REF!)/(#REF!-#REF!),#REF!-SQRT((1-#REF!)*(#REF!-#REF!)*(#REF!-#REF!)),#REF!+SQRT(#REF!*(#REF!-#REF!)*(#REF!-#REF!))) -> #REF! | T16: 10 | U16: ='3.a Observed Data'!Z14 -> 0.04797048 | V16: =V15+U16 -> 1 | X16: =Y15 -> 0.95202952 | Y16: =V16 -> 1 | Z16: 10
B17: Daily online reservation when price $180 | C17: =RAND() -> 0.16817027 | D17: =MAX(0,_xlfn.NORM.INV($C$17,$C$13,$D$13)) -> 5.8277105 | F17: =IF(#REF!>(#REF!-#REF!)/(#REF!-#REF!),#REF!-SQRT((1-#REF!)*(#REF!-#REF!)*(#REF!-#REF!)),#REF!+SQRT(#REF!*(#REF!-#REF!)*(#REF!-#REF!))) -> #REF!
F18: =IF(#REF!>(#REF!-#REF!)/(#REF!-#REF!),#REF!-SQRT((1-#REF!)*(#REF!-#REF!)*(#REF!-#REF!)),#REF!+SQRT(#REF!*(#REF!-#REF!)*(#REF!-#REF!))) -> #REF!
F19: =IF(#REF!>(#REF!-#REF!)/(#REF!-#REF!),#REF!-SQRT((1-#REF!)*(#REF!-#REF!)*(#REF!-#REF!)),#REF!+SQRT(#REF!*(#REF!-#REF!)*(#REF!-#REF!))) -> #REF!
F20: =IF(#REF!>(#REF!-#REF!)/(#REF!-#REF!),#REF!-SQRT((1-#REF!)*(#REF!-#REF!)*(#REF!-#REF!)),#REF!+SQRT(#REF!*(#REF!-#REF!)*(#REF!-#REF!))) -> #REF!
F21: =IF(#REF!>(#REF!-#REF!)/(#REF!-#REF!),#REF!-SQRT((1-#REF!)*(#REF!-#REF!)*(#REF!-#REF!)),#REF!+SQRT(#REF!*(#REF!-#REF!)*(#REF!-#REF!))) -> #REF!
F22: =IF(#REF!>(#REF!-#REF!)/(#REF!-#REF!),#REF!-SQRT((1-#REF!)*(#REF!-#REF!)*(#REF!-#REF!)),#REF!+SQRT(#REF!*(#REF!-#REF!)*(#REF!-#REF!))) -> #REF!
F23: =IF(#REF!>(#REF!-#REF!)/(#REF!-#REF!),#REF!-SQRT((1-#REF!)*(#REF!-#REF!)*(#REF!-#REF!)),#REF!+SQRT(#REF!*(#REF!-#REF!)*(#REF!-#REF!))) -> #REF!
F24: =IF(#REF!>(#REF!-#REF!)/(#REF!-#REF!),#REF!-SQRT((1-#REF!)*(#REF!-#REF!)*(#REF!-#REF!)),#REF!+SQRT(#REF!*(#REF!-#REF!)*(#REF!-#REF!))) -> #REF!
F25: =IF(#REF!>(#REF!-#REF!)/(#REF!-#REF!),#REF!-SQRT((1-#REF!)*(#REF!-#REF!)*(#REF!-#REF!)),#REF!+SQRT(#REF!*(#REF!-#REF!)*(#REF!-#REF!))) -> #REF!
F26: =IF(#REF!>(#REF!-#REF!)/(#REF!-#REF!),#REF!-SQRT((1-#REF!)*(#REF!-#REF!)*(#REF!-#REF!)),#REF!+SQRT(#REF!*(#REF!-#REF!)*(#REF!-#REF!))) -> #REF!
F27: =IF(#REF!>(#REF!-#REF!)/(#REF!-#REF!),#REF!-SQRT((1-#REF!)*(#REF!-#REF!)*(#REF!-#REF!)),#REF!+SQRT(#REF!*(#REF!-#REF!)*(#REF!-#REF!))) -> #REF!
F28: =IF(#REF!>(#REF!-#REF!)/(#REF!-#REF!),#REF!-SQRT((1-#REF!)*(#REF!-#REF!)*(#REF!-#REF!)),#REF!+SQRT(#REF!*(#REF!-#REF!)*(#REF!-#REF!))) -> #REF!
F29: =IF(#REF!>(#REF!-#REF!)/(#REF!-#REF!),#REF!-SQRT((1-#REF!)*(#REF!-#REF!)*(#REF!-#REF!)),#REF!+SQRT(#REF!*(#REF!-#REF!)*(#REF!-#REF!))) -> #REF!
... F275: =IF(#REF!>(#REF!-#REF!)/(#REF!-#REF!),#REF!-SQRT((1-#REF!)*(#REF!-#REF!)*(#REF!-#REF!)),#REF!+SQRT(#REF!*(#REF!-#REF!)*(#REF!-#REF!))) -> #REF!

Sheet 4.a Simulation
B2: SIMULATION OF 1000 TRIALS AT PRICE $120 WITH OVER BOOKING LEVEL AT 10% AND LATE CANCELLATION FEE AT 10% | T2: TRACKING CONVERGENCE OF OUTPUT MEANS | AF2: CONVERGENCE OF MEAN CHART FOR CALCULATED OUTPUTS AND TOTAL DAILY PROFIT | BA2: SIMULATION OF 1000 TRIALS AT PRICE $150 OVER BOOKING LEVEL AT 10% AND LATE CANCELLATION FEE AT 10% | BR2: TRACKING CONVERGENCE OF OUTPUT MEANS | CE2: CONVERGENCE OF MEAN CHART FOR CALCULATED OUTPUTS AND TOTAL DAILY PROFIT | DF2: SIMULATION OF 1000 TRIALS AT PRICE $180 OVER BOOKING LEVEL AT 10% AND LATE CANCELLATION FEE AT 10% | DX2: TRACKING CONVERGENCE OF OUTPUT MEANS | EJ2: CONVERGENCE OF MEAN CHART FOR CALCULATED OUTPUTS AND TOTAL DAILY PROFIT | FJ2: SIMULATION OF 1000 TRIALS AT PRICE $180 WITH OVER BOOKING LEVEL AT 15% AND LATE CANCELLATION FEE AT 20% | GB2: TRACKING CONVERGENCE OF OUTPUT MEANS | GN2: CONVERGENCE OF MEAN CHART FOR CALCULATED OUTPUTS AND TOTAL DAILY PROFIT | HM2: SIMULATION OF 1000 TRIALS AT PRICE $150 WITH OVER BOOKING LEVEL AT 15% AND LATE CANCELLATION FEE AT 20% | IE2: TRACKING CONVERGENCE OF OUTPUT MEANS | IQ2: CONVERGENCE OF MEAN CHART FOR CALCULATED OUTPUTS AND TOTAL DAILY PROFIT
B4: Simulation trials | C4: ='1.a Manager''s Page'!B4 -> Daily online reservations | D4: ='1.a Manager''s Page'!B5 -> Late cancellations percentage | E4: ='1.a Manager''s Page'!B6 -> Walk-in arrivals | F4: ='1.a Manager''s Page'!B7 -> Miscellaneuous daily expenses | G4: ='1.a Manager''s Page'!B22 -> Net demand | H4: ='1.a Manager''s Page'!B23 -> Room sold | I4: ='1.a Manager''s Page'!B24 -> Bumped guests | J4: ='1.a Manager''s Page'!B25 -> Revenue from stays | K4: ='1.a Manager''s Page'!B26 -> Total compensation cost | L4: ='1.a Manager''s Page'!B27 -> Total housekeeping cost | M4: ='1.a Manager''s Page'!B28 -> Total utilities cost | N4: ='1.a Manager''s Page'!B29 -> Total fixed inputs cost | O4: ='1.a Manager''s Page'!B30 -> Late no shows | P4: ='1.a Manager''s Page'!B31 -> Late cancellation fee revenue | Q4: ='1.a Manager''s Page'!B34 -> Total Daily Profit | R4: ='1.a Manager''s Page'!B35 -> Sold Out: Yes/ No | T4: =G4 -> Net demand | U4: =H4 -> Room sold | V4: =I4 -> Bumped guests | W4: =J4 -> Revenue from stays | X4: =K4 -> Total compensation cost | Y4: =L4 -> Total housekeeping cost | Z4: =M4 -> Total utilities cost | AA4: =N4 -> Total fixed inputs cost | ... AD4: =Q4 -> Total Daily Profit | AZ4: =B4 -> Simulation trials | BA4: =C4 -> Daily online reservations | BB4: =D4 -> Late cancellations percentage | BC4: =E4 -> Walk-in arrivals | BD4: =F4 -> Miscellaneuous daily expenses | BE4: =G4 -> Net demand | BF4: =H4 -> Room sold | BG4: =I4 -> Bumped guests | ... BP4: =R4 -> Sold Out: Yes/ No | BR4: =BE4 -> Net demand | BS4: =BF4 -> Room sold | BT4: =BG4 -> Bumped guests | BU4: =BH4 -> Revenue from stays | BV4: =BI4 -> Total compensation cost | BW4: =BJ4 -> Total housekeeping cost | BX4: =BK4 -> Total utilities cost | BY4: =BL4 -> Total fixed inputs cost | ... CB4: =BO4 -> Total Daily Profit | DF4: =AZ4 -> Simulation trials | DG4: =BA4 -> Daily online reservations | DH4: =BB4 -> Late cancellations percentage | DI4: =BC4 -> Walk-in arrivals | DJ4: =BD4 -> Miscellaneuous daily expenses | DK4: =BE4 -> Net demand | DL4: =BF4 -> Room sold | DM4: =BG4 -> Bumped guests | ... DV4: =BP4 -> Sold Out: Yes/ No | DX4: =DK4 -> Net demand | DY4: =DL4 -> Room sold | DZ4: =DM4 -> Bumped guests | EA4: =DN4 -> Revenue from stays | EB4: =DO4 -> Total compensation cost | EC4: =DP4 -> Total housekeeping cost | ED4: =DQ4 -> Total utilities cost | EE4: =DR4 -> Total fixed inputs cost | ... EH4: =DU4 -> Total Daily Profit | FJ4: =B4 -> Simulation trials | FK4: =C4 -> Daily online reservations | FL4: =D4 -> Late cancellations percentage | FM4: =E4 -> Walk-in arrivals | FN4: =F4 -> Miscellaneuous daily expenses | FO4: =G4 -> Net demand | FP4: =H4 -> Room sold | FQ4: =I4 -> Bumped guests | ... FZ4: =R4 -> Sold Out: Yes/ No | GB4: =BR4 -> Net demand | GC4: =BS4 -> Room sold | GD4: =BT4 -> Bumped guests | GE4: =BU4 -> Revenue from stays | GF4: =BV4 -> Total compensation cost | GG4: =BW4 -> Total housekeeping cost | GH4: =BX4 -> Total utilities cost | GI4: =BY4 -> Total fixed inputs cost | ... GL4: =CB4 -> Total Daily Profit | HM4: =B4 -> Simulation trials | HN4: =C4 -> Daily online reservations | HO4: =D4 -> Late cancellations percentage | HP4: =E4 -> Walk-in arrivals | HQ4: =F4 -> Miscellaneuous daily expenses | HR4: =G4 -> Net demand | HS4: =H4 -> Room sold | HT4: =I4 -> Bumped guests | ... IC4: =R4 -> Sold Out: Yes/ No | IE4: =GB4 -> Net demand | IF4: =GC4 -> Room sold | IG4: =GD4 -> Bumped guests | IH4: =GE4 -> Revenue from stays | II4: =GF4 -> Total compensation cost | IJ4: =GG4 -> Total housekeeping cost | IK4: =GH4 -> Total utilities cost | IL4: =GI4 -> Total fixed inputs cost | ... IO4: =GL4 -> Total Daily Profit
C5: ='1.c Model Simulated data'!H4 -> 5.8277105 | D5: ='1.c Model Simulated data'!H5 -> 0.25 | E5: ='1.c Model Simulated data'!H6 -> 8 | F5: ='1.c Model Simulated data'!H7 -> 454 | G5: ='1.c Model Simulated data'!C4 -> 13 | H5: ='1.c Model Simulated data'!C5 -> 13 | I5: ='1.c Model Simulated data'!C6 -> 0 | J5: ='1.c Model Simulated data'!C7 -> 2340 | K5: ='1.c Model Simulated data'!C8 -> 0 | L5: ='1.c Model Simulated data'!C9 -> 650 | M5: ='1.c Model Simulated data'!C10 -> 195 | N5: ='1.c Model Simulated data'!C12 -> 1924 | O5: ='1.c Model Simulated data'!C13 -> 1 | P5: ='1.c Model Simulated data'!C14 -> 18 | Q5: ='1.c Model Simulated data'!C17 -> 434 | R5: ='1.c Model Simulated data'!C18 -> No | BA5: ='1.c Model Simulated data'!H4 -> 5.8277105 | BB5: ='1.c Model Simulated data'!H5 -> 0.25 | BC5: ='1.c Model Simulated data'!H6 -> 8 | BD5: ='1.c Model Simulated data'!H7 -> 454 | BE5: ='1.c Model Simulated data'!C4 -> 13 | BF5: ='1.c Model Simulated data'!C5 -> 13 | BG5: ='1.c Model Simulated data'!C6 -> 0 | BH5: ='1.c Model Simulated data'!C7 -> 2340 | BI5: ='1.c Model Simulated data'!C8 -> 0 | BJ5: ='1.c Model Simulated data'!C9 -> 650 | BK5: ='1.c Model Simulated data'!C10 -> 195 | BL5: ='1.c Model Simulated data'!C12 -> 1924 | BM5: ='1.c Model Simulated data'!C13 -> 1 | BN5: ='1.c Model Simulated data'!C14 -> 18 | BO5: ='1.c Model Simulated data'!C17 -> 434 | BP5: ='1.c Model Simulated data'!C18 -> No | DG5: ='1.c Model Simulated data'!H4 -> 5.8277105 | DH5: ='1.c Model Simulated data'!H5 -> 0.25 | DI5: ='1.c Model Simulated data'!H6 -> 8 | DJ5: ='1.c Model Simulated data'!H7 -> 454 | DK5: ='1.c Model Simulated data'!C4 -> 13 | DL5: ='1.c Model Simulated data'!C5 -> 13 | DM5: ='1.c Model Simulated data'!C6 -> 0 | DN5: ='1.c Model Simulated data'!C7 -> 2340 | DO5: ='1.c Model Simulated data'!C8 -> 0 | DP5: ='1.c Model Simulated data'!C9 -> 650 | DQ5: ='1.c Model Simulated data'!C10 -> 195 | DR5: ='1.c Model Simulated data'!C12 -> 1924 | DS5: ='1.c Model Simulated data'!C13 -> 1 | DT5: ='1.c Model Simulated data'!C14 -> 18 | DU5: ='1.c Model Simulated data'!C17 -> 434 | DV5: ='1.c Model Simulated data'!C18 -> No | FK5: ='1.c Model Simulated data'!H4 -> 5.8277105 | FL5: ='1.c Model Simulated data'!H5 -> 0.25 | FM5: ='1.c Model Simulated data'!H6 -> 8 | FN5: ='1.c Model Simulated data'!H7 -> 454 | FO5: ='1.c Model Simulated data'!C4 -> 13 | FP5: ='1.c Model Simulated data'!C5 -> 13 | FQ5: ='1.c Model Simulated data'!C6 -> 0 | FR5: ='1.c Model Simulated data'!C7 -> 2340 | FS5: ='1.c Model Simulated data'!C8 -> 0 | FT5: ='1.c Model Simulated data'!C9 -> 650 | FU5: ='1.c Model Simulated data'!C10 -> 195 | FV5: ='1.c Model Simulated data'!C12 -> 1924 | FW5: ='1.c Model Simulated data'!C13 -> 1 | FX5: ='1.c Model Simulated data'!C14 -> 18 | FY5: ='1.c Model Simulated data'!C17 -> 434 | FZ5: ='1.c Model Simulated data'!C18 -> No | HN5: ='1.c Model Simulated data'!H4 -> 5.8277105 | HO5: ='1.c Model Simulated data'!H5 -> 0.25 | HP5: ='1.c Model Simulated data'!H6 -> 8 | HQ5: ='1.c Model Simulated data'!H7 -> 454 | HR5: ='1.c Model Simulated data'!C4 -> 13 | HS5: ='1.c Model Simulated data'!C5 -> 13 | HT5: ='1.c Model Simulated data'!C6 -> 0 | HU5: ='1.c Model Simulated data'!C7 -> 2340 | HV5: ='1.c Model Simulated data'!C8 -> 0 | HW5: ='1.c Model Simulated data'!C9 -> 650 | HX5: ='1.c Model Simulated data'!C10 -> 195 | HY5: ='1.c Model Simulated data'!C12 -> 1924 | HZ5: ='1.c Model Simulated data'!C13 -> 1 | IA5: ='1.c Model Simulated data'!C14 -> 18 | IB5: ='1.c Model Simulated data'!C17 -> 434 | IC5: ='1.c Model Simulated data'!C18 -> No
B6: 1 | C6: 22.305447 | D6: 0.05 | E6: 3 | F6: 477 | G6: 24 | H6: 22 | I6: 2 | J6: 2640 | K6: 240 | L6: 1000 | M6: 300 | N6: 2642 | O6: 1 | P6: 12 | Q6: 10 | R6: Yes | T6: =AVERAGE(G$6:G6) -> 24 | U6: =AVERAGE(H$6:H6) -> 22 | V6: =AVERAGE(I$6:I6) -> 2 | W6: =AVERAGE(J$6:J6) -> 2640 | X6: =AVERAGE(K$6:K6) -> 240 | Y6: =AVERAGE(L$6:L6) -> 1000 | Z6: =AVERAGE(M$6:M6) -> 300 | AA6: =AVERAGE(N$6:N6) -> 2642 | ... AD6: =AVERAGE(Q$6:Q6) -> 10 | AZ6: 1 | BA6: 17.013889 | BB6: 0.2 | BC6: 1 | BD6: 184 | BE6: 15 | BF6: 15 | BG6: 0 | BH6: 2250 | BI6: 0 | BJ6: 750 | BK6: 225 | BL6: 1784 | BM6: 3 | BN6: 45 | BO6: 511 | BP6: No | BR6: =AVERAGE(BE$6:BE6) -> 15 | BS6: =AVERAGE(BF$6:BF6) -> 15 | BT6: =AVERAGE(BG$6:BG6) -> 0 | BU6: =AVERAGE(BH$6:BH6) -> 2250 | BV6: =AVERAGE(BI$6:BI6) -> 0 | BW6: =AVERAGE(BJ$6:BJ6) -> 750 | BX6: =AVERAGE(BK$6:BK6) -> 225 | BY6: =AVERAGE(BL$6:BL6) -> 1784 | ... CB6: =AVERAGE(BO$6:BO6) -> 511 | DF6: 1 | DG6: 6.9312191 | DH6: 0.05 | DI6: 10 | DJ6: 338 | DK6: 17 | DL6: 17 | DM6: 0 | DN6: 3060 | DO6: 0 | DP6: 850 | DQ6: 255 | DR6: 2068 | DS6: 0 | DT6: 0 | DU6: 992 | DV6: No | DX6: =AVERAGE(DK$6:DK6) -> 17 | DY6: =AVERAGE(DL$6:DL6) -> 17 | DZ6: =AVERAGE(DM$6:DM6) -> 0 | EA6: =AVERAGE(DN$6:DN6) -> 3060 | EB6: =AVERAGE(DO$6:DO6) -> 0 | EC6: =AVERAGE(DP$6:DP6) -> 850 | ED6: =AVERAGE(DQ$6:DQ6) -> 255 | EE6: =AVERAGE(DR$6:DR6) -> 2068 | ... EH6: =AVERAGE(DU$6:DU6) -> 992 | FJ6: 1 | FK6: 5.5633831 | FL6: 0.2 | FM6: 0 | FN6: 119 | FO6: 5 | FP6: 5 | FQ6: 0 | FR6: 900 | FS6: 0 | FT6: 250 | FU6: 75 | FV6: 1069 | FW6: 1 | FX6: 36 | FY6: -133 | FZ6: No | GB6: =AVERAGE(FO$6:FO6) -> 5 | GC6: =AVERAGE(FP$6:FP6) -> 5 | GD6: =AVERAGE(FQ$6:FQ6) -> 0 | GE6: =AVERAGE(FR$6:FR6) -> 900 | GF6: =AVERAGE(FS$6:FS6) -> 0 | GG6: =AVERAGE(FT$6:FT6) -> 250 | GH6: =AVERAGE(FU$6:FU6) -> 75 | GI6: =AVERAGE(FV$6:FV6) -> 1069 | ... GL6: =AVERAGE(FY$6:FY6) -> -133 | HM6: 1 | HN6: 16.177445 | HO6: 0.05 | HP6: 1 | HQ6: 385 | HR6: 16 | HS6: 16 | HT6: 0 | HU6: 2400 | HV6: 0 | HW6: 800 | HX6: 240 | HY6: 2050 | HZ6: 1 | IA6: 30 | IB6: 380 | IC6: No | IE6: =AVERAGE(HR$6:HR6) -> 16 | IF6: =AVERAGE(HS$6:HS6) -> 16 | IG6: =AVERAGE(HT$6:HT6) -> 0 | IH6: =AVERAGE(HU$6:HU6) -> 2400 | II6: =AVERAGE(HV$6:HV6) -> 0 | IJ6: =AVERAGE(HW$6:HW6) -> 800 | IK6: =AVERAGE(HX$6:HX6) -> 240 | IL6: =AVERAGE(HY$6:HY6) -> 2050 | ... IO6: =AVERAGE(IB$6:IB6) -> 380
B7: 2 | C7: 21.053955 | D7: 0.05 | E7: 8 | F7: 414 | G7: 28 | H7: 22 | I7: 2 | J7: 2640 | K7: 240 | L7: 1000 | M7: 300 | N7: 2579 | O7: 1 | P7: 12 | Q7: 73 | R7: Yes | T7: =AVERAGE(G$6:G7) -> 26 | U7: =AVERAGE(H$6:H7) -> 22 | V7: =AVERAGE(I$6:I7) -> 2 | W7: =AVERAGE(J$6:J7) -> 2640 | X7: =AVERAGE(K$6:K7) -> 240 | Y7: =AVERAGE(L$6:L7) -> 1000 | Z7: =AVERAGE(M$6:M7) -> 300 | AA7: =AVERAGE(N$6:N7) -> 2610.5 | ... AD7: =AVERAGE(Q$6:Q7) -> 41.5 | AZ7: 2 | BA7: 23.087307 | BB7: 0.2 | BC7: 8 | BD7: 591 | BE7: 26 | BF7: 22 | BG7: 2 | BH7: 3300 | BI7: 300 | BJ7: 1000 | BK7: 300 | BL7: 2816 | BM7: 5 | BN7: 75 | BO7: 559 | BP7: Yes | BR7: =AVERAGE(BE$6:BE7) -> 20.5 | BS7: =AVERAGE(BF$6:BF7) -> 18.5 | BT7: =AVERAGE(BG$6:BG7) -> 1 | BU7: =AVERAGE(BH$6:BH7) -> 2775 | BV7: =AVERAGE(BI$6:BI7) -> 150 | BW7: =AVERAGE(BJ$6:BJ7) -> 875 | BX7: =AVERAGE(BK$6:BK7) -> 262.5 | BY7: =AVERAGE(BL$6:BL7) -> 2300 | ... CB7: =AVERAGE(BO$6:BO7) -> 535 | DF7: 2 | DG7: 6.8973869 | DH7: 0.25 | DI7: 8 | DJ7: 250 | DK7: 13 | DL7: 13 | DM7: 0 | DN7: 2340 | DO7: 0 | DP7: 650 | DQ7: 195 | DR7: 1720 | DS7: 2 | DT7: 36 | DU7: 656 | DV7: No | DX7: =AVERAGE(DK$6:DK7) -> 15 | DY7: =AVERAGE(DL$6:DL7) -> 15 | DZ7: =AVERAGE(DM$6:DM7) -> 0 | EA7: =AVERAGE(DN$6:DN7) -> 2700 | EB7: =AVERAGE(DO$6:DO7) -> 0 | EC7: =AVERAGE(DP$6:DP7) -> 750 | ED7: =AVERAGE(DQ$6:DQ7) -> 225 | EE7: =AVERAGE(DR$6:DR7) -> 1894 | ... EH7: =AVERAGE(DU$6:DU7) -> 824 | FJ7: 2 | FK7: 9.6665254 | FL7: 0.15 | FM7: 9 | FN7: 225 | FO7: 18 | FP7: 18 | FQ7: 0 | FR7: 3240 | FS7: 0 | FT7: 900 | FU7: 270 | FV7: 2020 | FW7: 1 | FX7: 36 | FY7: 1256 | FZ7: No | GB7: =AVERAGE(FO$6:FO7) -> 11.5 | GC7: =AVERAGE(FP$6:FP7) -> 11.5 | GD7: =AVERAGE(FQ$6:FQ7) -> 0 | GE7: =AVERAGE(FR$6:FR7) -> 2070 | GF7: =AVERAGE(FS$6:FS7) -> 0 | GG7: =AVERAGE(FT$6:FT7) -> 575 | GH7: =AVERAGE(FU$6:FU7) -> 172.5 | GI7: =AVERAGE(FV$6:FV7) -> 1544.5 | ... GL7: =AVERAGE(FY$6:FY7) -> 561.5 | HM7: 2 | HN7: 19.597592 | HO7: 0.05 | HP7: 2 | HQ7: 217 | HR7: 21 | HS7: 21 | HT7: 1 | HU7: 3150 | HV7: 150 | HW7: 1000 | HX7: 300 | HY7: 2292 | HZ7: 1 | IA7: 30 | IB7: 888 | IC7: Yes | IE7: =AVERAGE(HR$6:HR7) -> 18.5 | IF7: =AVERAGE(HS$6:HS7) -> 18.5 | IG7: =AVERAGE(HT$6:HT7) -> 0.5 | IH7: =AVERAGE(HU$6:HU7) -> 2775 | II7: =AVERAGE(HV$6:HV7) -> 75 | IJ7: =AVERAGE(HW$6:HW7) -> 900 | IK7: =AVERAGE(HX$6:HX7) -> 270 | IL7: =AVERAGE(HY$6:HY7) -> 2171 | ... IO7: =AVERAGE(IB$6:IB7) -> 634
B8: 3 | C8: 17.796057 | D8: 0.15 | E8: 3 | F8: 300 | G8: 18 | H8: 18 | I8: 0 | J8: 2160 | K8: 0 | L8: 900 | M8: 270 | N8: 2095 | O8: 3 | P8: 36 | Q8: 101 | R8: No | T8: =AVERAGE(G$6:G8) -> 23.333333 | U8: =AVERAGE(H$6:H8) -> 20.666667 | V8: =AVERAGE(I$6:I8) -> 1.3333333 | W8: =AVERAGE(J$6:J8) -> 2480 | X8: =AVERAGE(K$6:K8) -> 160 | Y8: =AVERAGE(L$6:L8) -> 966.66667 | Z8: =AVERAGE(M$6:M8) -> 290 | AA8: =AVERAGE(N$6:N8) -> 2438.6667 | ... AD8: =AVERAGE(Q$6:Q8) -> 61.333333 | AZ8: 3 | BA8: 15.241384 | BB8: 0.25 | BC8: 9 | BD8: 419 | BE8: 20 | BF8: 20 | BG8: 0 | BH8: 3000 | BI8: 0 | BJ8: 1000 | BK8: 300 | BL8: 2344 | BM8: 4 | BN8: 60 | BO8: 716 | BP8: Yes | BR8: =AVERAGE(BE$6:BE8) -> 20.333333 | BS8: =AVERAGE(BF$6:BF8) -> 19 | BT8: =AVERAGE(BG$6:BG8) -> 0.66666667 | BU8: =AVERAGE(BH$6:BH8) -> 2850 | BV8: =AVERAGE(BI$6:BI8) -> 100 | BW8: =AVERAGE(BJ$6:BJ8) -> 916.66667 | BX8: =AVERAGE(BK$6:BK8) -> 275 | BY8: =AVERAGE(BL$6:BL8) -> 2314.6667 | ... CB8: =AVERAGE(BO$6:BO8) -> 595.33333 | DF8: 3 | DG8: 7.3096127 | DH8: 0.25 | DI8: 1 | DJ8: 507 | DK8: 6 | DL8: 6 | DM8: 0 | DN8: 1080 | DO8: 0 | DP8: 300 | DQ8: 90 | DR8: 1522 | DS8: 2 | DT8: 36 | DU8: -406 | DV8: No | DX8: =AVERAGE(DK$6:DK8) -> 12 | DY8: =AVERAGE(DL$6:DL8) -> 12 | DZ8: =AVERAGE(DM$6:DM8) -> 0 | EA8: =AVERAGE(DN$6:DN8) -> 2160 | EB8: =AVERAGE(DO$6:DO8) -> 0 | EC8: =AVERAGE(DP$6:DP8) -> 600 | ED8: =AVERAGE(DQ$6:DQ8) -> 180 | EE8: =AVERAGE(DR$6:DR8) -> 1770 | ... EH8: =AVERAGE(DU$6:DU8) -> 414 | FJ8: 3 | FK8: 5.6367359 | FL8: 0.1 | FM8: 2 | FN8: 344 | FO8: 7 | FP8: 7 | FQ8: 0 | FR8: 1260 | FS8: 0 | FT8: 350 | FU8: 105 | FV8: 1424 | FW8: 1 | FX8: 36 | FY8: -128 | FZ8: No | GB8: =AVERAGE(FO$6:FO8) -> 10 | GC8: =AVERAGE(FP$6:FP8) -> 10 | GD8: =AVERAGE(FQ$6:FQ8) -> 0 | GE8: =AVERAGE(FR$6:FR8) -> 1800 | GF8: =AVERAGE(FS$6:FS8) -> 0 | GG8: =AVERAGE(FT$6:FT8) -> 500 | GH8: =AVERAGE(FU$6:FU8) -> 150 | GI8: =AVERAGE(FV$6:FV8) -> 1504.3333 | ... GL8: =AVERAGE(FY$6:FY8) -> 331.66667 | HM8: 3 | HN8: 16.753562 | HO8: 0.2 | HP8: 3 | HQ8: 388 | HR8: 17 | HS8: 17 | HT8: 0 | HU8: 2550 | HV8: 0 | HW8: 850 | HX8: 255 | HY8: 2118 | HZ8: 3 | IA8: 90 | IB8: 522 | IC8: No | IE8: =AVERAGE(HR$6:HR8) -> 18 | IF8: =AVERAGE(HS$6:HS8) -> 18 | IG8: =AVERAGE(HT$6:HT8) -> 0.33333333 | IH8: =AVERAGE(HU$6:HU8) -> 2700 | II8: =AVERAGE(HV$6:HV8) -> 50 | IJ8: =AVERAGE(HW$6:HW8) -> 883.33333 | IK8: =AVERAGE(HX$6:HX8) -> 265 | IL8: =AVERAGE(HY$6:HY8) -> 2153.3333 | ... IO8: =AVERAGE(IB$6:IB8) -> 596.66667
B9: 4 | C9: 15.618773 | D9: 0.05 | E9: 2 | F9: 555 | G9: 17 | H9: 17 | I9: 0 | J9: 2040 | K9: 0 | L9: 850 | M9: 255 | N9: 2285 | O9: 1 | P9: 12 | Q9: -233 | R9: No | T9: =AVERAGE(G$6:G9) -> 21.75 | U9: =AVERAGE(H$6:H9) -> 19.75 | V9: =AVERAGE(I$6:I9) -> 1 | W9: =AVERAGE(J$6:J9) -> 2370 | X9: =AVERAGE(K$6:K9) -> 120 | Y9: =AVERAGE(L$6:L9) -> 937.5 | Z9: =AVERAGE(M$6:M9) -> 281.25 | AA9: =AVERAGE(N$6:N9) -> 2400.25 | ... AD9: =AVERAGE(Q$6:Q9) -> -12.25 | AZ9: 4 | BA9: 18.889297 | BB9: 0.15 | BC9: 10 | BD9: 464 | BE9: 26 | BF9: 22 | BG9: 2 | BH9: 3300 | BI9: 300 | BJ9: 1000 | BK9: 300 | BL9: 2689 | BM9: 3 | BN9: 45 | BO9: 656 | BP9: Yes | BR9: =AVERAGE(BE$6:BE9) -> 21.75 | BS9: =AVERAGE(BF$6:BF9) -> 19.75 | BT9: =AVERAGE(BG$6:BG9) -> 1 | BU9: =AVERAGE(BH$6:BH9) -> 2962.5 | BV9: =AVERAGE(BI$6:BI9) -> 150 | BW9: =AVERAGE(BJ$6:BJ9) -> 937.5 | BX9: =AVERAGE(BK$6:BK9) -> 281.25 | BY9: =AVERAGE(BL$6:BL9) -> 2408.25 | ... CB9: =AVERAGE(BO$6:BO9) -> 610.5 | DF9: 4 | DG9: 8.6597735 | DH9: 0.1 | DI9: 1 | DJ9: 316 | DK9: 9 | DL9: 9 | DM9: 0 | DN9: 1620 | DO9: 0 | DP9: 450 | DQ9: 135 | DR9: 1526 | DS9: 1 | DT9: 18 | DU9: 112 | DV9: No | DX9: =AVERAGE(DK$6:DK9) -> 11.25 | DY9: =AVERAGE(DL$6:DL9) -> 11.25 | DZ9: =AVERAGE(DM$6:DM9) -> 0 | EA9: =AVERAGE(DN$6:DN9) -> 2025 | EB9: =AVERAGE(DO$6:DO9) -> 0 | EC9: =AVERAGE(DP$6:DP9) -> 562.5 | ED9: =AVERAGE(DQ$6:DQ9) -> 168.75 | EE9: =AVERAGE(DR$6:DR9) -> 1709 | ... EH9: =AVERAGE(DU$6:DU9) -> 338.5 | FJ9: 4 | FK9: 6.1965041 | FL9: 0.2 | FM9: 8 | FN9: 405 | FO9: 13 | FP9: 13 | FQ9: 0 | FR9: 2340 | FS9: 0 | FT9: 650 | FU9: 195 | FV9: 1875 | FW9: 1 | FX9: 36 | FY9: 501 | FZ9: No | GB9: =AVERAGE(FO$6:FO9) -> 10.75 | GC9: =AVERAGE(FP$6:FP9) -> 10.75 | GD9: =AVERAGE(FQ$6:FQ9) -> 0 | GE9: =AVERAGE(FR$6:FR9) -> 1935 | GF9: =AVERAGE(FS$6:FS9) -> 0 | GG9: =AVERAGE(FT$6:FT9) -> 537.5 | GH9: =AVERAGE(FU$6:FU9) -> 161.25 | GI9: =AVERAGE(FV$6:FV9) -> 1597 | ... GL9: =AVERAGE(FY$6:FY9) -> 374 | HM9: 4 | HN9: 16.729307 | HO9: 0.1 | HP9: 8 | HQ9: 148 | HR9: 23 | HS9: 23 | HT9: 3 | HU9: 3450 | HV9: 450 | HW9: 1000 | HX9: 300 | HY9: 2523 | HZ9: 2 | IA9: 60 | IB9: 987 | IC9: Yes | IE9: =AVERAGE(HR$6:HR9) -> 19.25 | IF9: =AVERAGE(HS$6:HS9) -> 19.25 | IG9: =AVERAGE(HT$6:HT9) -> 1 | IH9: =AVERAGE(HU$6:HU9) -> 2887.5 | II9: =AVERAGE(HV$6:HV9) -> 150 | IJ9: =AVERAGE(HW$6:HW9) -> 912.5 | IK9: =AVERAGE(HX$6:HX9) -> 273.75 | IL9: =AVERAGE(HY$6:HY9) -> 2245.75 | ... IO9: =AVERAGE(IB$6:IB9) -> 694.25
B10: 5 | C10: 21.327991 | D10: 0.25 | E10: 3 | F10: 433 | G10: 19 | H10: 19 | I10: 0 | J10: 2280 | K10: 0 | L10: 950 | M10: 285 | N10: 2293 | O10: 5 | P10: 60 | Q10: 47 | R10: No | T10: =AVERAGE(G$6:G10) -> 21.2 | U10: =AVERAGE(H$6:H10) -> 19.6 | V10: =AVERAGE(I$6:I10) -> 0.8 | W10: =AVERAGE(J$6:J10) -> 2352 | X10: =AVERAGE(K$6:K10) -> 96 | Y10: =AVERAGE(L$6:L10) -> 940 | Z10: =AVERAGE(M$6:M10) -> 282 | AA10: =AVERAGE(N$6:N10) -> 2378.8 | ... AD10: =AVERAGE(Q$6:Q10) -> -0.4 | AZ10: 5 | BA10: 18.357054 | BB10: 0.2 | BC10: 3 | BD10: 457 | BE10: 17 | BF10: 17 | BG10: 0 | BH10: 2550 | BI10: 0 | BJ10: 850 | BK10: 255 | BL10: 2187 | BM10: 4 | BN10: 60 | BO10: 423 | BP10: No | BR10: =AVERAGE(BE$6:BE10) -> 20.8 | BS10: =AVERAGE(BF$6:BF10) -> 19.2 | BT10: =AVERAGE(BG$6:BG10) -> 0.8 | BU10: =AVERAGE(BH$6:BH10) -> 2880 | BV10: =AVERAGE(BI$6:BI10) -> 120 | BW10: =AVERAGE(BJ$6:BJ10) -> 920 | BX10: =AVERAGE(BK$6:BK10) -> 276 | BY10: =AVERAGE(BL$6:BL10) -> 2364 | ... CB10: =AVERAGE(BO$6:BO10) -> 573 | DF10: 5 | DG10: 3.4174004 | DH10: 0.1 | DI10: 10 | DJ10: 354 | DK10: 13 | DL10: 13 | DM10: 0 | DN10: 2340 | DO10: 0 | DP10: 650 | DQ10: 195 | DR10: 1824 | DS10: 0 | DT10: 0 | DU10: 516 | DV10: No | DX10: =AVERAGE(DK$6:DK10) -> 11.6 | DY10: =AVERAGE(DL$6:DL10) -> 11.6 | DZ10: =AVERAGE(DM$6:DM10) -> 0 | EA10: =AVERAGE(DN$6:DN10) -> 2088 | EB10: =AVERAGE(DO$6:DO10) -> 0 | EC10: =AVERAGE(DP$6:DP10) -> 580 | ED10: =AVERAGE(DQ$6:DQ10) -> 174 | EE10: =AVERAGE(DR$6:DR10) -> 1732 | ... EH10: =AVERAGE(DU$6:DU10) -> 374 | FJ10: 5 | FK10: 5.5165983 | FL10: 0.05 | FM10: 1 | FN10: 296 | FO10: 7 | FP10: 7 | FQ10: 0 | FR10: 1260 | FS10: 0 | FT10: 350 | FU10: 105 | FV10: 1376 | FW10: 0 | FX10: 0 | FY10: -116 | FZ10: No | GB10: =AVERAGE(FO$6:FO10) -> 10 | GC10: =AVERAGE(FP$6:FP10) -> 10 | GD10: =AVERAGE(FQ$6:FQ10) -> 0 | GE10: =AVERAGE(FR$6:FR10) -> 1800 | GF10: =AVERAGE(FS$6:FS10) -> 0 | GG10: =AVERAGE(FT$6:FT10) -> 500 | GH10: =AVERAGE(FU$6:FU10) -> 150 | GI10: =AVERAGE(FV$6:FV10) -> 1552.8 | ... GL10: =AVERAGE(FY$6:FY10) -> 276 | HM10: 5 | HN10: 11.871016 | HO10: 0.15 | HP10: 9 | HQ10: 418 | HR10: 19 | HS10: 19 | HT10: 0 | HU10: 2850 | HV10: 0 | HW10: 950 | HX10: 285 | HY10: 2278 | HZ10: 2 | IA10: 60 | IB10: 632 | IC10: No | IE10: =AVERAGE(HR$6:HR10) -> 19.2 | IF10: =AVERAGE(HS$6:HS10) -> 19.2 | IG10: =AVERAGE(HT$6:HT10) -> 0.8 | IH10: =AVERAGE(HU$6:HU10) -> 2880 | II10: =AVERAGE(HV$6:HV10) -> 120 | IJ10: =AVERAGE(HW$6:HW10) -> 920 | IK10: =AVERAGE(HX$6:HX10) -> 276 | IL10: =AVERAGE(HY$6:HY10) -> 2252.2 | ... IO10: =AVERAGE(IB$6:IB10) -> 681.8
B11: 6 | C11: 19.788013 | D11: 0.2 | E11: 3 | F11: 203 | G11: 19 | H11: 19 | I11: 0 | J11: 2280 | K11: 0 | L11: 950 | M11: 285 | N11: 2063 | O11: 4 | P11: 48 | Q11: 265 | R11: No | T11: =AVERAGE(G$6:G11) -> 20.833333 | U11: =AVERAGE(H$6:H11) -> 19.5 | V11: =AVERAGE(I$6:I11) -> 0.66666667 | W11: =AVERAGE(J$6:J11) -> 2340 | X11: =AVERAGE(K$6:K11) -> 80 | Y11: =AVERAGE(L$6:L11) -> 941.66667 | Z11: =AVERAGE(M$6:M11) -> 282.5 | AA11: =AVERAGE(N$6:N11) -> 2326.1667 | ... AD11: =AVERAGE(Q$6:Q11) -> 43.833333 | AZ11: 6 | BA11: 18.044142 | BB11: 0.05 | BC11: 2 | BD11: 156 | BE11: 19 | BF11: 19 | BG11: 0 | BH11: 2850 | BI11: 0 | BJ11: 950 | BK11: 285 | BL11: 2016 | BM11: 1 | BN11: 15 | BO11: 849 | BP11: No | BR11: =AVERAGE(BE$6:BE11) -> 20.5 | BS11: =AVERAGE(BF$6:BF11) -> 19.166667 | BT11: =AVERAGE(BG$6:BG11) -> 0.66666667 | BU11: =AVERAGE(BH$6:BH11) -> 2875 | BV11: =AVERAGE(BI$6:BI11) -> 100 | BW11: =AVERAGE(BJ$6:BJ11) -> 925 | BX11: =AVERAGE(BK$6:BK11) -> 277.5 | BY11: =AVERAGE(BL$6:BL11) -> 2306 | ... CB11: =AVERAGE(BO$6:BO11) -> 619 | DF11: 6 | DG11: 7.4340107 | DH11: 0.25 | DI11: 1 | DJ11: 370 | DK11: 6 | DL11: 6 | DM11: 0 | DN11: 1080 | DO11: 0 | DP11: 300 | DQ11: 90 | DR11: 1385 | DS11: 2 | DT11: 36 | DU11: -269 | DV11: No | DX11: =AVERAGE(DK$6:DK11) -> 10.666667 | DY11: =AVERAGE(DL$6:DL11) -> 10.666667 | DZ11: =AVERAGE(DM$6:DM11) -> 0 | EA11: =AVERAGE(DN$6:DN11) -> 1920 | EB11: =AVERAGE(DO$6:DO11) -> 0 | EC11: =AVERAGE(DP$6:DP11) -> 533.33333 | ED11: =AVERAGE(DQ$6:DQ11) -> 160 | EE11: =AVERAGE(DR$6:DR11) -> 1674.1667 | ... EH11: =AVERAGE(DU$6:DU11) -> 266.83333 | FJ11: 6 | FK11: 9.227245 | FL11: 0.15 | FM11: 3 | FN11: 276 | FO11: 11 | FP11: 11 | FQ11: 0 | FR11: 1980 | FS11: 0 | FT11: 550 | FU11: 165 | FV11: 1616 | FW11: 1 | FX11: 36 | FY11: 400 | FZ11: No | GB11: =AVERAGE(FO$6:FO11) -> 10.166667 | GC11: =AVERAGE(FP$6:FP11) -> 10.166667 | GD11: =AVERAGE(FQ$6:FQ11) -> 0 | GE11: =AVERAGE(FR$6:FR11) -> 1830 | GF11: =AVERAGE(FS$6:FS11) -> 0 | GG11: =AVERAGE(FT$6:FT11) -> 508.33333 | GH11: =AVERAGE(FU$6:FU11) -> 152.5 | GI11: =AVERAGE(FV$6:FV11) -> 1563.3333 | ... GL11: =AVERAGE(FY$6:FY11) -> 296.66667 | HM11: 6 | HN11: 15.227579 | HO11: 0.05 | HP11: 3 | HQ11: 241 | HR11: 17 | HS11: 17 | HT11: 0 | HU11: 2550 | HV11: 0 | HW11: 850 | HX11: 255 | HY11: 1971 | HZ11: 1 | IA11: 30 | IB11: 609 | IC11: No | IE11: =AVERAGE(HR$6:HR11) -> 18.833333 | IF11: =AVERAGE(HS$6:HS11) -> 18.833333 | IG11: =AVERAGE(HT$6:HT11) -> 0.66666667 | IH11: =AVERAGE(HU$6:HU11) -> 2825 | II11: =AVERAGE(HV$6:HV11) -> 100 | IJ11: =AVERAGE(HW$6:HW11) -> 908.33333 | IK11: =AVERAGE(HX$6:HX11) -> 272.5 | IL11: =AVERAGE(HY$6:HY11) -> 2205.3333 | ... IO11: =AVERAGE(IB$6:IB11) -> 669.66667
B12: 7 | C12: 20.065666 | D12: 0.15 | E12: 9 | F12: 307 | G12: 26 | H12: 22 | I12: 2 | J12: 2640 | K12: 240 | L12: 1000 | M12: 300 | N12: 2472 | O12: 3 | P12: 36 | Q12: 204 | R12: Yes | T12: =AVERAGE(G$6:G12) -> 21.571429 | U12: =AVERAGE(H$6:H12) -> 19.857143 | V12: =AVERAGE(I$6:I12) -> 0.85714286 | W12: =AVERAGE(J$6:J12) -> 2382.8571 | X12: =AVERAGE(K$6:K12) -> 102.85714 | Y12: =AVERAGE(L$6:L12) -> 950 | Z12: =AVERAGE(M$6:M12) -> 285 | AA12: =AVERAGE(N$6:N12) -> 2347 | ... AD12: =AVERAGE(Q$6:Q12) -> 66.714286 | AZ12: 7 | BA12: 15.808306 | BB12: 0.05 | BC12: 3 | BD12: 520 | BE12: 18 | BF12: 18 | BG12: 0 | BH12: 2700 | BI12: 0 | BJ12: 900 | BK12: 270 | BL12: 2315 | BM12: 1 | BN12: 15 | BO12: 400 | BP12: No | BR12: =AVERAGE(BE$6:BE12) -> 20.142857 | BS12: =AVERAGE(BF$6:BF12) -> 19 | BT12: =AVERAGE(BG$6:BG12) -> 0.57142857 | BU12: =AVERAGE(BH$6:BH12) -> 2850 | BV12: =AVERAGE(BI$6:BI12) -> 85.714286 | BW12: =AVERAGE(BJ$6:BJ12) -> 921.42857 | BX12: =AVERAGE(BK$6:BK12) -> 276.42857 | BY12: =AVERAGE(BL$6:BL12) -> 2307.2857 | ... CB12: =AVERAGE(BO$6:BO12) -> 587.71429 | DF12: 7 | DG12: 7.0695048 | DH12: 0.1 | DI12: 3 | DJ12: 248 | DK12: 9 | DL12: 9 | DM12: 0 | DN12: 1620 | DO12: 0 | DP12: 450 | DQ12: 135 | DR12: 1458 | DS12: 1 | DT12: 18 | DU12: 180 | DV12: No | DX12: =AVERAGE(DK$6:DK12) -> 10.428571 | DY12: =AVERAGE(DL$6:DL12) -> 10.428571 | DZ12: =AVERAGE(DM$6:DM12) -> 0 | EA12: =AVERAGE(DN$6:DN12) -> 1877.1429 | EB12: =AVERAGE(DO$6:DO12) -> 0 | EC12: =AVERAGE(DP$6:DP12) -> 521.42857 | ED12: =AVERAGE(DQ$6:DQ12) -> 156.42857 | EE12: =AVERAGE(DR$6:DR12) -> 1643.2857 | ... EH12: =AVERAGE(DU$6:DU12) -> 254.42857 | FJ12: 7 | FK12: 7.4313953 | FL12: 0.05 | FM12: 3 | FN12: 305 | FO12: 10 | FP12: 10 | FQ12: 0 | FR12: 1800 | FS12: 0 | FT12: 500 | FU12: 150 | FV12: 1580 | FW12: 0 | FX12: 0 | FY12: 220 | FZ12: No | GB12: =AVERAGE(FO$6:FO12) -> 10.142857 | GC12: =AVERAGE(FP$6:FP12) -> 10.142857 | GD12: =AVERAGE(FQ$6:FQ12) -> 0 | GE12: =AVERAGE(FR$6:FR12) -> 1825.7143 | GF12: =AVERAGE(FS$6:FS12) -> 0 | GG12: =AVERAGE(FT$6:FT12) -> 507.14286 | GH12: =AVERAGE(FU$6:FU12) -> 152.14286 | GI12: =AVERAGE(FV$6:FV12) -> 1565.7143 | ... GL12: =AVERAGE(FY$6:FY12) -> 285.71429 | HM12: 7 | HN12: 19.304518 | HO12: 0.15 | HP12: 3 | HQ12: 572 | HR12: 19 | HS12: 19 | HT12: 0 | HU12: 2850 | HV12: 0 | HW12: 950 | HX12: 285 | HY12: 2432 | HZ12: 3 | IA12: 90 | IB12: 508 | IC12: No | IE12: =AVERAGE(HR$6:HR12) -> 18.857143 | IF12: =AVERAGE(HS$6:HS12) -> 18.857143 | IG12: =AVERAGE(HT$6:HT12) -> 0.57142857 | IH12: =AVERAGE(HU$6:HU12) -> 2828.5714 | II12: =AVERAGE(HV$6:HV12) -> 85.714286 | IJ12: =AVERAGE(HW$6:HW12) -> 914.28571 | IK12: =AVERAGE(HX$6:HX12) -> 274.28571 | IL12: =AVERAGE(HY$6:HY12) -> 2237.7143 | ... IO12: =AVERAGE(IB$6:IB12) -> 646.57143
B13: 8 | C13: 29.944888 | D13: 0.05 | E13: 2 | F13: 409 | G13: 31 | H13: 22 | I13: 2 | J13: 2640 | K13: 240 | L13: 1000 | M13: 300 | N13: 2574 | O13: 1 | P13: 12 | Q13: 78 | R13: Yes | T13: =AVERAGE(G$6:G13) -> 22.75 | U13: =AVERAGE(H$6:H13) -> 20.125 | V13: =AVERAGE(I$6:I13) -> 1 | W13: =AVERAGE(J$6:J13) -> 2415 | X13: =AVERAGE(K$6:K13) -> 120 | Y13: =AVERAGE(L$6:L13) -> 956.25 | Z13: =AVERAGE(M$6:M13) -> 286.875 | AA13: =AVERAGE(N$6:N13) -> 2375.375 | ... AD13: =AVERAGE(Q$6:Q13) -> 68.125 | AZ13: 8 | BA13: 18.372454 | BB13: 0.15 | BC13: 4 | BD13: 117 | BE13: 19 | BF13: 19 | BG13: 0 | BH13: 2850 | BI13: 0 | BJ13: 950 | BK13: 285 | BL13: 1977 | BM13: 3 | BN13: 45 | BO13: 918 | BP13: No | BR13: =AVERAGE(BE$6:BE13) -> 20 | BS13: =AVERAGE(BF$6:BF13) -> 19 | BT13: =AVERAGE(BG$6:BG13) -> 0.5 | BU13: =AVERAGE(BH$6:BH13) -> 2850 | BV13: =AVERAGE(BI$6:BI13) -> 75 | BW13: =AVERAGE(BJ$6:BJ13) -> 925 | BX13: =AVERAGE(BK$6:BK13) -> 277.5 | BY13: =AVERAGE(BL$6:BL13) -> 2266 | ... CB13: =AVERAGE(BO$6:BO13) -> 629 | DF13: 8 | DG13: 7.3752793 | DH13: 0.15 | DI13: 2 | DJ13: 214 | DK13: 8 | DL13: 8 | DM13: 0 | DN13: 1440 | DO13: 0 | DP13: 400 | DQ13: 120 | DR13: 1359 | DS13: 1 | DT13: 18 | DU13: 99 | DV13: No | DX13: =AVERAGE(DK$6:DK13) -> 10.125 | DY13: =AVERAGE(DL$6:DL13) -> 10.125 | DZ13: =AVERAGE(DM$6:DM13) -> 0 | EA13: =AVERAGE(DN$6:DN13) -> 1822.5 | EB13: =AVERAGE(DO$6:DO13) -> 0 | EC13: =AVERAGE(DP$6:DP13) -> 506.25 | ED13: =AVERAGE(DQ$6:DQ13) -> 151.875 | EE13: =AVERAGE(DR$6:DR13) -> 1607.75 | ... EH13: =AVERAGE(DU$6:DU13) -> 235 | FJ13: 8 | FK13: 8.6280748 | FL13: 0.25 | FM13: 8 | FN13: 582 | FO13: 15 | FP13: 15 | FQ13: 0 | FR13: 2700 | FS13: 0 | FT13: 750 | FU13: 225 | FV13: 2182 | FW13: 2 | FX13: 72 | FY13: 590 | FZ13: No | GB13: =AVERAGE(FO$6:FO13) -> 10.75 | GC13: =AVERAGE(FP$6:FP13) -> 10.75 | GD13: =AVERAGE(FQ$6:FQ13) -> 0 | GE13: =AVERAGE(FR$6:FR13) -> 1935 | GF13: =AVERAGE(FS$6:FS13) -> 0 | GG13: =AVERAGE(FT$6:FT13) -> 537.5 | GH13: =AVERAGE(FU$6:FU13) -> 161.25 | GI13: =AVERAGE(FV$6:FV13) -> 1642.75 | ... GL13: =AVERAGE(FY$6:FY13) -> 323.75 | HM13: 8 | HN13: 14.404942 | HO13: 0.15 | HP13: 3 | HQ13: 152 | HR13: 15 | HS13: 15 | HT13: 0 | HU13: 2250 | HV13: 0 | HW13: 750 | HX13: 225 | HY13: 1752 | HZ13: 2 | IA13: 60 | IB13: 558 | IC13: No | IE13: =AVERAGE(HR$6:HR13) -> 18.375 | IF13: =AVERAGE(HS$6:HS13) -> 18.375 | IG13: =AVERAGE(HT$6:HT13) -> 0.5 | IH13: =AVERAGE(HU$6:HU13) -> 2756.25 | II13: =AVERAGE(HV$6:HV13) -> 75 | IJ13: =AVERAGE(HW$6:HW13) -> 893.75 | IK13: =AVERAGE(HX$6:HX13) -> 268.125 | IL13: =AVERAGE(HY$6:HY13) -> 2177 | ... IO13: =AVERAGE(IB$6:IB13) -> 635.5
B14: 9 | C14: 24.514969 | D14: 0.1 | E14: 4 | F14: 238 | G14: 27 | H14: 22 | I14: 2 | J14: 2640 | K14: 240 | L14: 1000 | M14: 300 | N14: 2403 | O14: 2 | P14: 24 | Q14: 261 | R14: Yes | T14: =AVERAGE(G$6:G14) -> 23.222222 | U14: =AVERAGE(H$6:H14) -> 20.333333 | V14: =AVERAGE(I$6:I14) -> 1.1111111 | W14: =AVERAGE(J$6:J14) -> 2440 | X14: =AVERAGE(K$6:K14) -> 133.33333 | Y14: =AVERAGE(L$6:L14) -> 961.11111 | Z14: =AVERAGE(M$6:M14) -> 288.33333 | AA14: =AVERAGE(N$6:N14) -> 2378.4444 | ... AD14: =AVERAGE(Q$6:Q14) -> 89.555556 | AZ14: 9 | BA14: 12.493647 | BB14: 0.05 | BC14: 9 | BD14: 241 | BE14: 20 | BF14: 20 | BG14: 0 | BH14: 3000 | BI14: 0 | BJ14: 1000 | BK14: 300 | BL14: 2166 | BM14: 1 | BN14: 15 | BO14: 849 | BP14: Yes | BR14: =AVERAGE(BE$6:BE14) -> 20 | BS14: =AVERAGE(BF$6:BF14) -> 19.111111 | BT14: =AVERAGE(BG$6:BG14) -> 0.44444444 | BU14: =AVERAGE(BH$6:BH14) -> 2866.6667 | BV14: =AVERAGE(BI$6:BI14) -> 66.666667 | BW14: =AVERAGE(BJ$6:BJ14) -> 933.33333 | BX14: =AVERAGE(BK$6:BK14) -> 280 | BY14: =AVERAGE(BL$6:BL14) -> 2254.8889 | ... CB14: =AVERAGE(BO$6:BO14) -> 653.44444 | DF14: 9 | DG14: 6.6302736 | DH14: 0.15 | DI14: 8 | DJ14: 357 | DK14: 14 | DL14: 14 | DM14: 0 | DN14: 2520 | DO14: 0 | DP14: 700 | DQ14: 210 | DR14: 1892 | DS14: 1 | DT14: 18 | DU14: 646 | DV14: No | DX14: =AVERAGE(DK$6:DK14) -> 10.555556 | DY14: =AVERAGE(DL$6:DL14) -> 10.555556 | DZ14: =AVERAGE(DM$6:DM14) -> 0 | EA14: =AVERAGE(DN$6:DN14) -> 1900 | EB14: =AVERAGE(DO$6:DO14) -> 0 | EC14: =AVERAGE(DP$6:DP14) -> 527.77778 | ED14: =AVERAGE(DQ$6:DQ14) -> 158.33333 | EE14: =AVERAGE(DR$6:DR14) -> 1639.3333 | ... EH14: =AVERAGE(DU$6:DU14) -> 280.66667 | FJ14: 9 | FK14: 5.4456649 | FL14: 0.25 | FM14: 3 | FN14: 510 | FO14: 7 | FP14: 7 | FQ14: 0 | FR14: 1260 | FS14: 0 | FT14: 350 | FU14: 105 | FV14: 1590 | FW14: 1 | FX14: 36 | FY14: -294 | FZ14: No | GB14: =AVERAGE(FO$6:FO14) -> 10.333333 | GC14: =AVERAGE(FP$6:FP14) -> 10.333333 | GD14: =AVERAGE(FQ$6:FQ14) -> 0 | GE14: =AVERAGE(FR$6:FR14) -> 1860 | GF14: =AVERAGE(FS$6:FS14) -> 0 | GG14: =AVERAGE(FT$6:FT14) -> 516.66667 | GH14: =AVERAGE(FU$6:FU14) -> 155 | GI14: =AVERAGE(FV$6:FV14) -> 1636.8889 | ... GL14: =AVERAGE(FY$6:FY14) -> 255.11111 | HM14: 9 | HN14: 18.873342 | HO14: 0.2 | HP14: 0 | HQ14: 205 | HR14: 15 | HS14: 15 | HT14: 0 | HU14: 2250 | HV14: 0 | HW14: 750 | HX14: 225 | HY14: 1805 | HZ14: 4 | IA14: 120 | IB14: 565 | IC14: No | IE14: =AVERAGE(HR$6:HR14) -> 18 | IF14: =AVERAGE(HS$6:HS14) -> 18 | IG14: =AVERAGE(HT$6:HT14) -> 0.44444444 | IH14: =AVERAGE(HU$6:HU14) -> 2700 | II14: =AVERAGE(HV$6:HV14) -> 66.666667 | IJ14: =AVERAGE(HW$6:HW14) -> 877.77778 | IK14: =AVERAGE(HX$6:HX14) -> 263.33333 | IL14: =AVERAGE(HY$6:HY14) -> 2135.6667 | ... IO14: =AVERAGE(IB$6:IB14) -> 627.66667
B15: 10 | C15: 23.666352 | D15: 0.05 | E15: 8 | F15: 261 | G15: 31 | H15: 22 | I15: 2 | J15: 2640 | K15: 240 | L15: 1000 | M15: 300 | N15: 2426 | O15: 1 | P15: 12 | Q15: 226 | R15: Yes | T15: =AVERAGE(G$6:G15) -> 24 | U15: =AVERAGE(H$6:H15) -> 20.5 | V15: =AVERAGE(I$6:I15) -> 1.2 | W15: =AVERAGE(J$6:J15) -> 2460 | X15: =AVERAGE(K$6:K15) -> 144 | Y15: =AVERAGE(L$6:L15) -> 965 | Z15: =AVERAGE(M$6:M15) -> 289.5 | AA15: =AVERAGE(N$6:N15) -> 2383.2 | ... AD15: =AVERAGE(Q$6:Q15) -> 103.2 | AZ15: 10 | BA15: 12.693674 | BB15: 0.05 | BC15: 2 | BD15: 111 | BE15: 14 | BF15: 14 | BG15: 0 | BH15: 2100 | BI15: 0 | BJ15: 700 | BK15: 210 | BL15: 1646 | BM15: 1 | BN15: 15 | BO15: 469 | BP15: No | BR15: =AVERAGE(BE$6:BE15) -> 19.4 | BS15: =AVERAGE(BF$6:BF15) -> 18.6 | BT15: =AVERAGE(BG$6:BG15) -> 0.4 | BU15: =AVERAGE(BH$6:BH15) -> 2790 | BV15: =AVERAGE(BI$6:BI15) -> 60 | BW15: =AVERAGE(BJ$6:BJ15) -> 910 | BX15: =AVERAGE(BK$6:BK15) -> 273 | BY15: =AVERAGE(BL$6:BL15) -> 2194 | ... CB15: =AVERAGE(BO$6:BO15) -> 635 | DF15: 10 | DG15: 6.2280126 | DH15: 0.1 | DI15: 10 | DJ15: 413 | DK15: 15 | DL15: 15 | DM15: 0 | DN15: 2700 | DO15: 0 | DP15: 750 | DQ15: 225 | DR15: 2013 | DS15: 1 | DT15: 18 | DU15: 705 | DV15: No | DX15: =AVERAGE(DK$6:DK15) -> 11 | DY15: =AVERAGE(DL$6:DL15) -> 11 | DZ15: =AVERAGE(DM$6:DM15) -> 0 | EA15: =AVERAGE(DN$6:DN15) -> 1980 | EB15: =AVERAGE(DO$6:DO15) -> 0 | EC15: =AVERAGE(DP$6:DP15) -> 550 | ED15: =AVERAGE(DQ$6:DQ15) -> 165 | EE15: =AVERAGE(DR$6:DR15) -> 1676.7 | ... EH15: =AVERAGE(DU$6:DU15) -> 323.1 | FJ15: 10 | FK15: 5.5152187 | FL15: 0.15 | FM15: 2 | FN15: 244 | FO15: 7 | FP15: 7 | FQ15: 0 | FR15: 1260 | FS15: 0 | FT15: 350 | FU15: 105 | FV15: 1324 | FW15: 1 | FX15: 36 | FY15: -28 | FZ15: No | GB15: =AVERAGE(FO$6:FO15) -> 10 | GC15: =AVERAGE(FP$6:FP15) -> 10 | GD15: =AVERAGE(FQ$6:FQ15) -> 0 | GE15: =AVERAGE(FR$6:FR15) -> 1800 | GF15: =AVERAGE(FS$6:FS15) -> 0 | GG15: =AVERAGE(FT$6:FT15) -> 500 | GH15: =AVERAGE(FU$6:FU15) -> 150 | GI15: =AVERAGE(FV$6:FV15) -> 1605.6 | ... GL15: =AVERAGE(FY$6:FY15) -> 226.8 | HM15: 10 | HN15: 20.531246 | HO15: 0.15 | HP15: 3 | HQ15: 493 | HR15: 21 | HS15: 21 | HT15: 1 | HU15: 3150 | HV15: 150 | HW15: 1000 | HX15: 300 | HY15: 2568 | HZ15: 3 | IA15: 90 | IB15: 672 | IC15: Yes | IE15: =AVERAGE(HR$6:HR15) -> 18.3 | IF15: =AVERAGE(HS$6:HS15) -> 18.3 | IG15: =AVERAGE(HT$6:HT15) -> 0.5 | IH15: =AVERAGE(HU$6:HU15) -> 2745 | II15: =AVERAGE(HV$6:HV15) -> 75 | IJ15: =AVERAGE(HW$6:HW15) -> 890 | IK15: =AVERAGE(HX$6:HX15) -> 267 | IL15: =AVERAGE(HY$6:HY15) -> 2178.9 | ... IO15: =AVERAGE(IB$6:IB15) -> 632.1
B16: 11 | C16: 22.377781 | D16: 0.15 | E16: 3 | F16: 131 | G16: 22 | H16: 22 | I16: 2 | J16: 2640 | K16: 240 | L16: 1000 | M16: 300 | N16: 2296 | O16: 3 | P16: 36 | Q16: 380 | R16: Yes | T16: =AVERAGE(G$6:G16) -> 23.818182 | U16: =AVERAGE(H$6:H16) -> 20.636364 | V16: =AVERAGE(I$6:I16) -> 1.2727273 | W16: =AVERAGE(J$6:J16) -> 2476.3636 | X16: =AVERAGE(K$6:K16) -> 152.72727 | Y16: =AVERAGE(L$6:L16) -> 968.18182 | Z16: =AVERAGE(M$6:M16) -> 290.45455 | AA16: =AVERAGE(N$6:N16) -> 2375.2727 | ... AD16: =AVERAGE(Q$6:Q16) -> 128.36364 | AZ16: 11 | BA16: 19.443439 | BB16: 0.1 | BC16: 1 | BD16: 296 | BE16: 18 | BF16: 18 | BG16: 0 | BH16: 2700 | BI16: 0 | BJ16: 900 | BK16: 270 | BL16: 2091 | BM16: 2 | BN16: 30 | BO16: 639 | BP16: No | BR16: =AVERAGE(BE$6:BE16) -> 19.272727 | BS16: =AVERAGE(BF$6:BF16) -> 18.545455 | BT16: =AVERAGE(BG$6:BG16) -> 0.36363636 | BU16: =AVERAGE(BH$6:BH16) -> 2781.8182 | BV16: =AVERAGE(BI$6:BI16) -> 54.545455 | BW16: =AVERAGE(BJ$6:BJ16) -> 909.09091 | BX16: =AVERAGE(BK$6:BK16) -> 272.72727 | BY16: =AVERAGE(BL$6:BL16) -> 2184.6364 | ... CB16: =AVERAGE(BO$6:BO16) -> 635.36364 | DF16: 11 | DG16: 6.8709089 | DH16: 0.05 | DI16: 1 | DJ16: 526 | DK16: 8 | DL16: 8 | DM16: 0 | DN16: 1440 | DO16: 0 | DP16: 400 | DQ16: 120 | DR16: 1671 | DS16: 0 | DT16: 0 | DU16: -231 | DV16: No | DX16: =AVERAGE(DK$6:DK16) -> 10.727273 | DY16: =AVERAGE(DL$6:DL16) -> 10.727273 | DZ16: =AVERAGE(DM$6:DM16) -> 0 | EA16: =AVERAGE(DN$6:DN16) -> 1930.9091 | EB16: =AVERAGE(DO$6:DO16) -> 0 | EC16: =AVERAGE(DP$6:DP16) -> 536.36364 | ED16: =AVERAGE(DQ$6:DQ16) -> 160.90909 | EE16: =AVERAGE(DR$6:DR16) -> 1676.1818 | ... EH16: =AVERAGE(DU$6:DU16) -> 272.72727 | FJ16: 11 | FK16: 6.004362 | FL16: 0.15 | FM16: 3 | FN16: 265 | FO16: 8 | FP16: 8 | FQ16: 0 | FR16: 1440 | FS16: 0 | FT16: 400 | FU16: 120 | FV16: 1410 | FW16: 1 | FX16: 36 | FY16: 66 | FZ16: No | GB16: =AVERAGE(FO$6:FO16) -> 9.8181818 | GC16: =AVERAGE(FP$6:FP16) -> 9.8181818 | GD16: =AVERAGE(FQ$6:FQ16) -> 0 | GE16: =AVERAGE(FR$6:FR16) -> 1767.2727 | GF16: =AVERAGE(FS$6:FS16) -> 0 | GG16: =AVERAGE(FT$6:FT16) -> 490.90909 | GH16: =AVERAGE(FU$6:FU16) -> 147.27273 | GI16: =AVERAGE(FV$6:FV16) -> 1587.8182 | ... GL16: =AVERAGE(FY$6:FY16) -> 212.18182 | HM16: 11 | HN16: 13.872642 | HO16: 0.2 | HP16: 1 | HQ16: 147 | HR16: 12 | HS16: 12 | HT16: 0 | HU16: 1800 | HV16: 0 | HW16: 600 | HX16: 180 | HY16: 1552 | HZ16: 3 | IA16: 90 | IB16: 338 | IC16: No | IE16: =AVERAGE(HR$6:HR16) -> 17.727273 | IF16: =AVERAGE(HS$6:HS16) -> 17.727273 | IG16: =AVERAGE(HT$6:HT16) -> 0.45454545 | IH16: =AVERAGE(HU$6:HU16) -> 2659.0909 | II16: =AVERAGE(HV$6:HV16) -> 68.181818 | IJ16: =AVERAGE(HW$6:HW16) -> 863.63636 | IK16: =AVERAGE(HX$6:HX16) -> 259.09091 | IL16: =AVERAGE(HY$6:HY16) -> 2121.9091 | ... IO16: =AVERAGE(IB$6:IB16) -> 605.36364
B17: 12 | C17: 21.397847 | D17: 0.05 | E17: 3 | F17: 197 | G17: 23 | H17: 22 | I17: 2 | J17: 2640 | K17: 240 | L17: 1000 | M17: 300 | N17: 2362 | O17: 1 | P17: 12 | Q17: 290 | R17: Yes | T17: =AVERAGE(G$6:G17) -> 23.75 | U17: =AVERAGE(H$6:H17) -> 20.75 | V17: =AVERAGE(I$6:I17) -> 1.3333333 | W17: =AVERAGE(J$6:J17) -> 2490 | X17: =AVERAGE(K$6:K17) -> 160 | Y17: =AVERAGE(L$6:L17) -> 970.83333 | Z17: =AVERAGE(M$6:M17) -> 291.25 | AA17: =AVERAGE(N$6:N17) -> 2374.1667 | ... AD17: =AVERAGE(Q$6:Q17) -> 141.83333 | AZ17: 12 | BA17: 19.206835 | BB17: 0.05 | BC17: 3 | BD17: 142 | BE17: 21 | BF17: 21 | BG17: 1 | BH17: 3150 | BI17: 150 | BJ17: 1000 | BK17: 300 | BL17: 2217 | BM17: 1 | BN17: 15 | BO17: 948 | BP17: Yes | BR17: =AVERAGE(BE$6:BE17) -> 19.416667 | BS17: =AVERAGE(BF$6:BF17) -> 18.75 | BT17: =AVERAGE(BG$6:BG17) -> 0.41666667 | BU17: =AVERAGE(BH$6:BH17) -> 2812.5 | BV17: =AVERAGE(BI$6:BI17) -> 62.5 | BW17: =AVERAGE(BJ$6:BJ17) -> 916.66667 | BX17: =AVERAGE(BK$6:BK17) -> 275 | BY17: =AVERAGE(BL$6:BL17) -> 2187.3333 | ... CB17: =AVERAGE(BO$6:BO17) -> 661.41667 | DF17: 12 | DG17: 8.4273039 | DH17: 0.15 | DI17: 1 | DJ17: 199 | DK17: 8 | DL17: 8 | DM17: 0 | DN17: 1440 | DO17: 0 | DP17: 400 | DQ17: 120 | DR17: 1344 | DS17: 1 | DT17: 18 | DU17: 114 | DV17: No | DX17: =AVERAGE(DK$6:DK17) -> 10.5 | DY17: =AVERAGE(DL$6:DL17) -> 10.5 | DZ17: =AVERAGE(DM$6:DM17) -> 0 | EA17: =AVERAGE(DN$6:DN17) -> 1890 | EB17: =AVERAGE(DO$6:DO17) -> 0 | EC17: =AVERAGE(DP$6:DP17) -> 525 | ED17: =AVERAGE(DQ$6:DQ17) -> 157.5 | EE17: =AVERAGE(DR$6:DR17) -> 1648.5 | ... EH17: =AVERAGE(DU$6:DU17) -> 259.5 | FJ17: 12 | FK17: 7.9584204 | FL17: 0.2 | FM17: 0 | FN17: 342 | FO17: 6 | FP17: 6 | FQ17: 0 | FR17: 1080 | FS17: 0 | FT17: 300 | FU17: 90 | FV17: 1357 | FW17: 2 | FX17: 72 | FY17: -205 | FZ17: No | GB17: =AVERAGE(FO$6:FO17) -> 9.5 | GC17: =AVERAGE(FP$6:FP17) -> 9.5 | GD17: =AVERAGE(FQ$6:FQ17) -> 0 | GE17: =AVERAGE(FR$6:FR17) -> 1710 | GF17: =AVERAGE(FS$6:FS17) -> 0 | GG17: =AVERAGE(FT$6:FT17) -> 475 | GH17: =AVERAGE(FU$6:FU17) -> 142.5 | GI17: =AVERAGE(FV$6:FV17) -> 1568.5833 | ... GL17: =AVERAGE(FY$6:FY17) -> 177.41667 | HM17: 12 | HN17: 23.648388 | HO17: 0.2 | HP17: 1 | HQ17: 547 | HR17: 20 | HS17: 20 | HT17: 0 | HU17: 3000 | HV17: 0 | HW17: 1000 | HX17: 300 | HY17: 2472 | HZ17: 5 | IA17: 150 | IB17: 678 | IC17: Yes | IE17: =AVERAGE(HR$6:HR17) -> 17.916667 | IF17: =AVERAGE(HS$6:HS17) -> 17.916667 | IG17: =AVERAGE(HT$6:HT17) -> 0.41666667 | IH17: =AVERAGE(HU$6:HU17) -> 2687.5 | II17: =AVERAGE(HV$6:HV17) -> 62.5 | IJ17: =AVERAGE(HW$6:HW17) -> 875 | IK17: =AVERAGE(HX$6:HX17) -> 262.5 | IL17: =AVERAGE(HY$6:HY17) -> 2151.0833 | ... IO17: =AVERAGE(IB$6:IB17) -> 611.41667
... B1005: 1000 | C1005: 27.658115 | D1005: 0.1 | E1005: 8 | F1005: 259 | G1005: 33 | H1005: 22 | I1005: 2 | J1005: 2640 | K1005: 240 | L1005: 1000 | M1005: 300 | N1005: 2424 | O1005: 3 | P1005: 36 | Q1005: 252 | R1005: Yes | T1005: =AVERAGE(G$6:G1005) -> 23.36 | U1005: =AVERAGE(H$6:H1005) -> 20.753 | V1005: =AVERAGE(I$6:I1005) -> 1.367 | W1005: =AVERAGE(J$6:J1005) -> 2490.36 | X1005: =AVERAGE(K$6:K1005) -> 164.04 | Y1005: =AVERAGE(L$6:L1005) -> 969.3 | Z1005: =AVERAGE(M$6:M1005) -> 290.79 | AA1005: =AVERAGE(N$6:N1005) -> 2406.509 | ... AD1005: =AVERAGE(Q$6:Q1005) -> 119.299 | AZ1005: 1000 | BA1005: 19.087943 | BB1005: 0.05 | BC1005: 1 | BD1005: 284 | BE1005: 19 | BF1005: 19 | BG1005: 0 | BH1005: 2850 | BI1005: 0 | BJ1005: 950 | BK1005: 285 | BL1005: 2144 | BM1005: 1 | BN1005: 15 | BO1005: 721 | BP1005: No | BR1005: =AVERAGE(BE$6:BE1005) -> 19.626 | BS1005: =AVERAGE(BF$6:BF1005) -> 18.857 | BT1005: =AVERAGE(BG$6:BG1005) -> 0.677 | BU1005: =AVERAGE(BH$6:BH1005) -> 2828.55 | BV1005: =AVERAGE(BI$6:BI1005) -> 101.55 | BW1005: =AVERAGE(BJ$6:BJ1005) -> 909 | BX1005: =AVERAGE(BK$6:BK1005) -> 272.7 | BY1005: =AVERAGE(BL$6:BL1005) -> 2250.854 | ... CB1005: =AVERAGE(BO$6:BO1005) -> 612.511 | DF1005: 1000 | DG1005: 5.2195834 | DH1005: 0.2 | DI1005: 9 | DJ1005: 175 | DK1005: 13 | DL1005: 13 | DM1005: 0 | DN1005: 2340 | DO1005: 0 | DP1005: 650 | DQ1005: 195 | DR1005: 1645 | DS1005: 1 | DT1005: 18 | DU1005: 713 | DV1005: No | DX1005: =AVERAGE(DK$6:DK1005) -> 10.323 | DY1005: =AVERAGE(DL$6:DL1005) -> 10.323 | DZ1005: =AVERAGE(DM$6:DM1005) -> 0 | EA1005: =AVERAGE(DN$6:DN1005) -> 1858.14 | EB1005: =AVERAGE(DO$6:DO1005) -> 0 | EC1005: =AVERAGE(DP$6:DP1005) -> 516.15 | ED1005: =AVERAGE(DQ$6:DQ1005) -> 154.845 | EE1005: =AVERAGE(DR$6:DR1005) -> 1650.046 | ... EH1005: =AVERAGE(DU$6:DU1005) -> 223.214 | FJ1005: 1000 | FK1005: 7.7289446 | FL1005: 0.15 | FM1005: 6 | FN1005: 550 | FO1005: 13 | FP1005: 13 | FQ1005: 0 | FR1005: 2340 | FS1005: 0 | FT1005: 650 | FU1005: 195 | FV1005: 2020 | FW1005: 1 | FX1005: 36 | FY1005: 356 | FZ1005: No | GB1005: =AVERAGE(FO$6:FO1005) -> 10.109 | GC1005: =AVERAGE(FP$6:FP1005) -> 10.109 | GD1005: =AVERAGE(FQ$6:FQ1005) -> 0 | GE1005: =AVERAGE(FR$6:FR1005) -> 1819.62 | GF1005: =AVERAGE(FS$6:FS1005) -> 0 | GG1005: =AVERAGE(FT$6:FT1005) -> 505.45 | GH1005: =AVERAGE(FU$6:FU1005) -> 151.635 | GI1005: =AVERAGE(FV$6:FV1005) -> 1633.698 | ... GL1005: =AVERAGE(FY$6:FY1005) -> 216.378 | HM1005: 1000 | HN1005: 16.025595 | HO1005: 0.1 | HP1005: 8 | HQ1005: 133 | HR1005: 22 | HS1005: 22 | HT1005: 2 | HU1005: 3300 | HV1005: 300 | HW1005: 1000 | HX1005: 300 | HY1005: 2358 | HZ1005: 2 | IA1005: 60 | IB1005: 1002 | IC1005: Yes | IE1005: =AVERAGE(HR$6:HR1005) -> 19.651 | IF1005: =AVERAGE(HS$6:HS1005) -> 19.073 | IG1005: =AVERAGE(HT$6:HT1005) -> 0.999 | IH1005: =AVERAGE(HU$6:HU1005) -> 2860.95 | II1005: =AVERAGE(HV$6:HV1005) -> 149.85 | IJ1005: =AVERAGE(HW$6:HW1005) -> 903.7 | IK1005: =AVERAGE(HX$6:HX1005) -> 271.11 | IL1005: =AVERAGE(HY$6:HY1005) -> 2300.206 | ... IO1005: =AVERAGE(IB$6:IB1005) -> 634.004

Sheet 4.b Output Summary
AQ1: CREATING BOX PLOT
C3: Daily Profit when Room Nightly Rate Is (Over-booking Level at 10% and Cancellation Fee at 10%)
C4: 120 | D4: 150 | E4: 180 | AQ4: Daily Profit at $120 | AR4: Daily Profit at $150 | AS4: Daily Profit at $180
A5: Mean | C5: =AVERAGE('4.a Simulation'!$Q$6:$Q$1005) -> 119.299 | D5: =AVERAGE('4.a Simulation'!$BO$6:$BO$1005) -> 612.511 | E5: =AVERAGE('4.a Simulation'!$DU$6:$DU$1005) -> 223.214 | AP5: 1 | AQ5: 10 | AR5: 511 | AS5: 992
A6: Standard Deviation | C6: =_xlfn.STDEV.S('4.a Simulation'!$Q$6:$Q$1005) -> 166.39287 | D6: =_xlfn.STDEV.S('4.a Simulation'!$BO$6:$BO$1005) -> 231.48987 | E6: =_xlfn.STDEV.S('4.a Simulation'!$DU$6:$DU$1005) -> 382.82403 | AP6: 2 | AQ6: 73 | AR6: 559 | AS6: 656
A7: Minimum | C7: =MIN('4.a Simulation'!$Q$6:$Q$1005) -> -436 | D7: =MIN('4.a Simulation'!$BO$6:$BO$1005) -> -276 | E7: =MIN('4.a Simulation'!$DU$6:$DU$1005) -> -840 | AP7: 3 | AQ7: 101 | AR7: 716 | AS7: -406
A8: Maximum | C8: =MAX('4.a Simulation'!$Q$6:$Q$1005) -> 444 | D8: =MAX('4.a Simulation'!$BO$6:$BO$1005) -> 1048 | E8: =MAX('4.a Simulation'!$DU$6:$DU$1005) -> 1263 | AP8: 4 | AQ8: -233 | AR8: 656 | AS8: 112
A9: Probability of Loss | C9: =COUNTIF('4.a Simulation'!$Q$6:$Q$1005,"<0")/1000 -> 0.269 | D9: =COUNTIF('4.a Simulation'!$BO$6:$BO$1005,"<0")/1000 -> 0.014 | E9: =COUNTIF('4.a Simulation'!$DU$6:$DU$1005,"<0")/1000 -> 0.315 | AP9: 5 | AQ9: 47 | AR9: 423 | AS9: 516
AP10: 6 | AQ10: 265 | AR10: 849 | AS10: -269
AP11: 7 | AQ11: 204 | AR11: 400 | AS11: 180
A12: 95% Confidendence limits for the mean | AP12: 8 | AQ12: 78 | AR12: 918 | AS12: 99
AP13: 9 | AQ13: 261 | AR13: 849 | AS13: 646
A14: UCL | C14: =C$5+_xlfn.T.INV.2T(0.05,1000-1)*C$6/SQRT(1000) -> 129.62446 | D14: =D$5+_xlfn.T.INV.2T(0.05,1000-1)*D$6/SQRT(1000) -> 626.87603 | E14: =E$5+_xlfn.T.INV.2T(0.05,1000-1)*E$6/SQRT(1000) -> 246.97003 | AP14: 10 | AQ14: 226 | AR14: 469 | AS14: 705
A15: LCL | C15: =C$5-_xlfn.T.INV.2T(0.05,1000-1)*C$6/SQRT(1000) -> 108.97354 | D15: =D$5-_xlfn.T.INV.2T(0.05,1000-1)*D$6/SQRT(1000) -> 598.14597 | E15: =E$5-_xlfn.T.INV.2T(0.05,1000-1)*E$6/SQRT(1000) -> 199.45797 | AP15: 11 | AQ15: 380 | AR15: 639 | AS15: -231
AP16: 12 | AQ16: 290 | AR16: 948 | AS16: 114
AP17: 13 | AQ17: 9 | AR17: 917 | AS17: 671
A18: Lower Quartile | C18: =QUARTILE('4.a Simulation'!$Q$6:$Q$1005,1) -> -10 | D18: =QUARTILE('4.a Simulation'!$BO$6:$BO$1005,1) -> 472.5 | E18: =QUARTILE('4.a Simulation'!$DU$6:$DU$1005,1) -> -65.25 | AP18: 14 | AQ18: -51 | AR18: 762 | AS18: 99
A19: Upper Quartile | C19: =QUARTILE('4.a Simulation'!$Q$6:$Q$1005,3) -> 253.75 | D19: =QUARTILE('4.a Simulation'!$BO$6:$BO$1005,3) -> 786 | E19: =QUARTILE('4.a Simulation'!$DU$6:$DU$1005,3) -> 516 | AP19: 15 | AQ19: -196 | AR19: 564 | AS19: 69
A20: IQR | C20: =C19-C18 -> 263.75 | D20: =D19-D18 -> 313.5 | E20: =E19-E18 -> 581.25 | AP20: 16 | AQ20: 31 | AR20: 910 | AS20: 568
A21: 90th Quartile | C21: =PERCENTILE('4.a Simulation'!$Q$6:$Q$1005,0.9) -> 340.1 | D21: =PERCENTILE('4.a Simulation'!$BO$6:$BO$1005,0.9) -> 885 | E21: =PERCENTILE('4.a Simulation'!$DU$6:$DU$1005,0.9) -> 768.1 | AP21: 17 | AQ21: -103 | AR21: 32 | AS21: -39
A22: 10th Quartile | C22: =PERCENTILE('4.a Simulation'!$Q$6:$Q$1005,0.1) -> -75.1 | D22: =PERCENTILE('4.a Simulation'!$BO$6:$BO$1005,0.1) -> 300.7 | E22: =PERCENTILE('4.a Simulation'!$DU$6:$DU$1005,0.1) -> -241.1 | AP22: 18 | AQ22: -45 | AR22: 495 | AS22: -392
AP23: 19 | AQ23: 44 | AR23: 205 | AS23: 311
AP24: 20 | AQ24: 193 | AR24: 886 | AS24: 141
B25: Daily Profit when Room Nightly Rate at $120 (Over-booking Level at 10% and Cancellation Fee at 10%) | R25: Daily Profit when Room Nightly Rate at $150 (Over-booking Level at 10% and Cancellation Fee at 10%) | AD25: Daily Profit when Room Nightly Rate at $180 (Over-booking Level at 10% and Cancellation Fee at 10%) | AP25: 21 | AQ25: 260 | AR25: 699 | AS25: 667
B26: Bin ($) | C26: Frequency | E26: Bin ($) | F26: Frequency | G26: %Frequency | I26: Daily Profit ($) | R26: Bin | S26: Frequency | U26: Bin ($) | V26: Frequency | W26: %Frequency | Y26: Daily Profit ($) | AD26: Bin | AE26: Frequency | AG26: Bin ($) | AH26: Frequency | AI26: %Frequency | AK26: Daily Profit ($) | AP26: 22 | AQ26: 83 | AR26: 374 | AS26: 523
B27: -500 | C27: 0 | E27: =B28 -> -400 | F27: =C28 -> 3 | G27: =F27/$F$37 -> 0.003 | R27: -300 | S27: 0 | U27: =R28 -> -200 | V27: =S28 -> 2 | W27: =V27/$V$41 -> 0.002 | AD27: -900 | AE27: 0 | AG27: =AD28 -> -700 | AH27: =AE28 -> 1 | AI27: =AH27/$AH$38 -> 0.001 | AK27: Mean | AL27: 223.214 | AP27: 23 | AQ27: 163 | AR27: 536 | AS27: 325
B28: -400 | C28: 3 | E28: =B29 -> -300 | F28: =C29 -> 9 | G28: =F28/$F$37 -> 0.009 | I28: Mean | J28: 119.299 | R28: -200 | S28: 2 | U28: =R29 -> -100 | V28: =S29 -> 4 | W28: =V28/$V$41 -> 0.004 | Y28: Mean | Z28: 612.511 | AD28: -700 | AE28: 1 | AG28: =AD29 -> -500 | AH28: =AE29 -> 8 | AI28: =AH28/$AH$38 -> 0.008 | AK28: Standard Error | AL28: 12.105959 | AP28: 24 | AQ28: 132 | AR28: 724 | AS28: 75
B29: -300 | C29: 9 | E29: =B30 -> -200 | F29: =C30 -> 19 | G29: =F29/$F$37 -> 0.019 | I29: Standard Error | J29: 5.2618047 | R29: -100 | S29: 4 | U29: =R30 -> 0 | V29: =S30 -> 8 | W29: =V29/$V$41 -> 0.008 | Y29: Standard Error | Z29: 7.3203525 | AD29: -500 | AE29: 8 | AG29: =AD30 -> -300 | AH29: =AE30 -> 54 | AI29: =AH29/$AH$38 -> 0.054 | AK29: Median | AL29: 179.5 | AP29: 25 | AQ29: 272 | AR29: 500 | AS29: 814
B30: -200 | C30: 19 | E30: =B31 -> -100 | F30: =C31 -> 40 | G30: =F30/$F$37 -> 0.04 | I30: Median | J30: 117.5 | R30: 0 | S30: 8 | U30: =R31 -> 100 | V30: =S31 -> 14 | W30: =V30/$V$41 -> 0.014 | Y30: Median | Z30: 643 | AD30: -300 | AE30: 54 | AG30: =AD31 -> -100 | AH30: =AE31 -> 158 | AI30: =AH30/$AH$38 -> 0.158 | AK30: Mode | AL30: -39 | AP30: 26 | AQ30: 16 | AR30: 766 | AS30: -238
B31: -100 | C31: 40 | E31: =B32 -> 0 | F31: =C32 -> 200 | G31: =F31/$F$37 -> 0.2 | I31: Mode | J31: -22 | R31: 100 | S31: 14 | U31: =R32 -> 200 | V31: =S32 -> 23 | W31: =V31/$V$41 -> 0.023 | Y31: Mode | Z31: 619 | AD31: -100 | AE31: 158 | AG31: =AD32 -> 100 | AH31: =AE32 -> 212 | AI31: =AH31/$AH$38 -> 0.212 | AK31: Standard Deviation | AL31: 382.82403 | AP31: 27 | AQ31: 324 | AR31: 411 | AS31: 149
B32: 0 | C32: 200 | E32: =B33 -> 100 | F32: =C33 -> 197 | G32: =F32/$F$37 -> 0.197 | I32: Standard Deviation | J32: 166.39287 | R32: 200 | S32: 23 | U32: =R33 -> 300 | V32: =S33 -> 49 | W32: =V32/$V$41 -> 0.049 | Y32: Standard Deviation | Z32: 231.48987 | AD32: 100 | AE32: 212 | AG32: =AD33 -> 300 | AH32: =AE33 -> 176 | AI32: =AH32/$AH$38 -> 0.176 | AK32: Sample Variance | AL32: 146554.24 | AP32: 28 | AQ32: 88 | AR32: 605 | AS32: 840
B33: 100 | C33: 197 | E33: =B34 -> 200 | F33: =C34 -> 182 | G33: =F33/$F$37 -> 0.182 | I33: Sample Variance | J33: 27686.588 | R33: 300 | S33: 49 | U33: =R34 -> 400 | V33: =S34 -> 78 | W33: =V33/$V$41 -> 0.078 | Y33: Sample Variance | Z33: 53587.561 | AD33: 300 | AE33: 176 | AG33: =AD34 -> 500 | AH33: =AE34 -> 131 | AI33: =AH33/$AH$38 -> 0.131 | AK33: Kurtosis | AL33: -0.55431628 | AP33: 29 | AQ33: 210 | AR33: 619 | AS33: 270
B34: 200 | C34: 182 | E34: =B35 -> 300 | F34: =C35 -> 177 | G34: =F34/$F$37 -> 0.177 | I34: Kurtosis | J34: -0.28501842 | R34: 400 | S34: 78 | U34: =R35 -> 500 | V34: =S35 -> 111 | W34: =V34/$V$41 -> 0.111 | Y34: Kurtosis | Z34: 0.32686472 | AD34: 500 | AE34: 131 | AG34: =AD35 -> 700 | AH34: =AE35 -> 129 | AI34: =AH34/$AH$38 -> 0.129 | AK34: Skewness | AL34: 0.31647688 | AP34: 30 | AQ34: 88 | AR34: 903 | AS34: 138
B35: 300 | C35: 177 | E35: =B36 -> 400 | F35: =C36 -> 158 | G35: =F35/$F$37 -> 0.158 | I35: Skewness | J35: -0.2934687 | R35: 500 | S35: 111 | U35: =R36 -> 600 | V35: =S36 -> 138 | W35: =V35/$V$41 -> 0.138 | Y35: Skewness | Z35: -0.68229186 | AD35: 700 | AE35: 129 | AG35: =AD36 -> 900 | AH35: =AE36 -> 81 | AI35: =AH35/$AH$38 -> 0.081 | AK35: Range | AL35: 2103 | AP35: 31 | AQ35: 240 | AR35: 705 | AS35: -57
B36: 400 | C36: 158 | E36: =B37 -> 500 | F36: =C37 -> 15 | G36: =F36/$F$37 -> 0.015 | I36: Range | J36: 880 | R36: 600 | S36: 138 | U36: =R37 -> 700 | V36: =S37 -> 183 | W36: =V36/$V$41 -> 0.183 | Y36: Range | Z36: 1324 | AD36: 900 | AE36: 81 | AG36: =AD37 -> 1100 | AH36: =AE37 -> 39 | AI36: =AH36/$AH$38 -> 0.039 | AK36: Minimum | AL36: -840 | AP36: 32 | AQ36: 154 | AR36: 262 | AS36: 508
B37: 500 | C37: 15 | E37: Total | F37: =SUM(F27:F36) -> 1000 | G37: =SUM(G27:G36) -> 1 | I37: Minimum | J37: -436 | R37: 700 | S37: 183 | U37: =R38 -> 800 | V37: =S38 -> 158 | W37: =V37/$V$41 -> 0.158 | Y37: Minimum | Z37: -276 | AD37: 1100 | AE37: 39 | AG37: =AD38 -> 1300 | AH37: =AE38 -> 11 | AI37: =AH37/$AH$38 -> 0.011 | AK37: Maximum | AL37: 1263 | AP37: 33 | AQ37: -37 | AR37: 944 | AS37: 6
B38: More | C38: 0 | I38: Maximum | J38: 444 | R38: 800 | S38: 158 | U38: =R39 -> 900 | V38: =S39 -> 143 | W38: =V38/$V$41 -> 0.143 | Y38: Maximum | Z38: 1048 | AD38: 1300 | AE38: 11 | AG38: Total | AH38: =SUM(AH27:AH37) -> 1000 | AK38: Sum | AL38: 223214 | AP38: 34 | AQ38: -38 | AR38: 765 | AS38: -35
I39: Sum | J39: 119299 | R39: 900 | S39: 143 | U39: =R40 -> 1000 | V39: =S40 -> 85 | W39: =V39/$V$41 -> 0.085 | Y39: Sum | Z39: 612511 | AD39: More | AE39: 0 | AK39: Count | AL39: 1000 | AP39: 35 | AQ39: 38 | AR39: 555 | AS39: -192
I40: Count | J40: 1000 | R40: 1000 | S40: 85 | U40: =R41 -> 1100 | V40: =S41 -> 4 | W40: =V40/$V$41 -> 0.004 | Y40: Count | Z40: 1000 | AP40: 36 | AQ40: 310 | AR40: 715 | AS40: -434
R41: 1100 | S41: 4 | U41: Total | V41: =SUM(V27:V40) -> 1000 | W41: =SUM(W27:W40) -> 1 | AP41: 37 | AQ41: 289 | AR41: 448 | AS41: -378
R42: More | S42: 0 | AP42: 38 | AQ42: 265 | AR42: 668 | AS42: 328
AP43: 39 | AQ43: 358 | AR43: 233 | AS43: 252
AP44: 40 | AQ44: -116 | AR44: 564 | AS44: 307
AP45: 41 | AQ45: 317 | AR45: 377 | AS45: -14
AP46: 42 | AQ46: 164 | AR46: 509 | AS46: -59
AP47: 43 | AQ47: -25 | AR47: 871 | AS47: 319
AP48: 44 | AQ48: -55 | AR48: 876 | AS48: 336
AP49: 45 | AQ49: -107 | AR49: 792 | AS49: 10
AP50: 46 | AQ50: 68 | AR50: 878 | AS50: 596
AP51: 47 | AQ51: -7 | AR51: 619 | AS51: 802
AP52: 48 | AQ52: -372 | AR52: 709 | AS52: 633
AP53: 49 | AQ53: 344 | AR53: 749 | AS53: 877
AP54: 50 | AQ54: 126 | AR54: 263 | AS54: 64
... AP76: 72 | AQ76: -8 | AR76: 777 | AS76: 58
I77: Daily Profit ($) | AP77: 73 | AQ77: 200 | AR77: 452 | AS77: -39
J78: Nightly Room Rate at $120 | K78: Nightly Room Rate at $150 | L78: Nightly Room Rate at $180 | AP78: 74 | AQ78: 246 | AR78: 986 | AS78: -378
I79: Mean | J79: 119.299 | K79: 612.511 | L79: 223.214 | AP79: 75 | AQ79: 44 | AR79: 1005 | AS79: -231
I80: Standard Error | J80: 5.2618047 | K80: 7.3203525 | L80: 12.105959 | AP80: 76 | AQ80: -53 | AR80: 415 | AS80: -33
I81: Median | J81: 117.5 | K81: 643 | L81: 179.5 | AP81: 77 | AQ81: -43 | AR81: 470 | AS81: -156
I82: Mode | J82: -22 | K82: 619 | L82: -39 | AP82: 78 | AQ82: 62 | AR82: 788 | AS82: 104
I83: Standard Deviation | J83: 166.39287 | K83: 231.48987 | L83: 382.82403 | AP83: 79 | AQ83: 135 | AR83: 703 | AS83: 425
I84: Sample Variance | J84: 27686.588 | K84: 53587.561 | L84: 146554.24 | AP84: 80 | AQ84: -259 | AR84: 708 | AS84: 76
I85: Kurtosis | J85: -0.28501842 | K85: 0.32686472 | L85: -0.55431628 | AP85: 81 | AQ85: 258 | AR85: 393 | AS85: -264
I86: Skewness | J86: -0.2934687 | K86: -0.68229186 | L86: 0.31647688 | AP86: 82 | AQ86: 146 | AR86: 489 | AS86: -413
I87: Range | J87: 880 | K87: 1324 | L87: 2103 | AP87: 83 | AQ87: 415 | AR87: 603 | AS87: -110
I88: Minimum | J88: -436 | K88: -276 | L88: -840 | AP88: 84 | AQ88: 340 | AR88: 278 | AS88: 613
I89: Maximum | J89: 444 | K89: 1048 | L89: 1263 | AP89: 85 | AQ89: 199 | AR89: 906 | AS89: 478
I90: Sum | J90: 119299 | K90: 612511 | L90: 223214 | AP90: 86 | AQ90: -82 | AR90: 605 | AS90: -233
I91: Count | J91: 1000 | K91: 1000 | L91: 1000 | AP91: 87 | AQ91: 336 | AR91: 461 | AS91: 160
AP92: 88 | AQ92: 106 | AR92: 847 | AS92: 175
AP93: 89 | AQ93: 188 | AR93: 481 | AS93: -33
AP94: 90 | AQ94: 110 | AR94: 710 | AS94: 423
AP95: 91 | AQ95: -45 | AR95: 835 | AS95: 286
AP96: 92 | AQ96: 77 | AR96: 620 | AS96: 399
AP97: 93 | AQ97: 185 | AR97: 115 | AS97: 12
AP98: 94 | AQ98: 234 | AR98: 144 | AS98: 549
AP99: 95 | AQ99: -245 | AR99: 642 | AS99: 266
AP100: 96 | AQ100: 157 | AR100: 309 | AS100: -62
AP101: 97 | AQ101: 99 | AR101: 971 | AS101: 213
AP102: 98 | AQ102: 315 | AR102: 895 | AS102: -12
AP103: 99 | AQ103: -168 | AR103: 700 | AS103: 557
... AP1004: 1000 | AQ1004: 252 | AR1004: 721 | AS1004: 713

Sheet 4. Risk Analysis
C2: RISK PROFILING
C4: Daily Profit when Room Nightly Rate at $120 (Over-booking Level at 10% and Cancellation Fee at 10%) | M4: Daily Profit when Room Nightly Rate at $150 (Over-booking Level at 10% and Cancellation Fee at 10%) | AA4: Daily Profit when Room Nightly Rate at $180 (Over-booking Level at 10% and Cancellation Fee at 10%)
C5: From -$400 to -$200 | D5: From -$200 to $0 | E5: From $0 to $200 | F5: From $200 to $400 | G5: From $400 to $600 | H5: Over $600 | I5: Total | M5: From -$400 to -$200 | N5: From -$200 to $0 | O5: From $0 to $200 | P5: From $200 to $400 | Q5: From $400 to $600 | R5: From $600 to $800 | S5: From $800 to $1000 | T5: From $1000 to $1200 | U5: Over $1200 | V5: Total | AA5: From -$400 to -$200 | AB5: From -$200 to $0 | AC5: From $0 to $200 | AD5: From $200 to $400 | AE5: From $400 to $600 | AF5: From $600 to $800 | AG5: From $800 to $1000 | AH5: From $1000 to $1200 | AI5: From $1200 to $1400 | AJ5: Over $1400 | AK5: Total
B6: Probability | C6: =COUNTIFS('4.a Simulation'!$Q$6:$Q$1005,"<=-200")/1000 -> 0.031 | D6: =COUNTIFS('4.a Simulation'!$Q$6:$Q$1005,">-200",'4.a Simulation'!$Q$6:$Q$1005,"<=0")/1000 -> 0.24 | E6: =COUNTIFS('4.a Simulation'!$Q$6:$Q$1005,">0",'4.a Simulation'!$Q$6:$Q$1005,"<=200")/1000 -> 0.379 | F6: =COUNTIFS('4.a Simulation'!$Q$6:$Q$1005,">200",'4.a Simulation'!$Q$6:$Q$1005,"<=400")/1000 -> 0.335 | G6: =COUNTIFS('4.a Simulation'!$Q$6:$Q$1005,">400",'4.a Simulation'!$Q$6:$Q$1005,"<=600")/1000 -> 0.015 | H6: =COUNTIF('4.a Simulation'!$Q$6:$Q$1005,">600")/1000 -> 0 | I6: =SUM(C6:H6) -> 1 | L6: Probability | M6: =COUNTIF('4.a Simulation'!$BO$6:$BO$1005,"<=-200")/1000 -> 0.002 | N6: =COUNTIFS('4.a Simulation'!$BO$6:$BO$1005,">-200",'4.a Simulation'!$BO$6:$BO$1005,"<=0")/1000 -> 0.012 | O6: =COUNTIFS('4.a Simulation'!$BO$6:$BO$1005,">0",'4.a Simulation'!$BO$6:$BO$1005,"<=200")/1000 -> 0.037 | P6: =COUNTIFS('4.a Simulation'!$BO$6:$BO$1005,">200",'4.a Simulation'!$BO$6:$BO$1005,"<=400")/1000 -> 0.127 | Q6: =COUNTIFS('4.a Simulation'!$BO$6:$BO$1005,">400",'4.a Simulation'!$BO$6:$BO$1005,"<=600")/1000 -> 0.249 | R6: =COUNTIFS('4.a Simulation'!$BO$6:$BO$1005,">600",'4.a Simulation'!$BO$6:$BO$1005,"<=800")/1000 -> 0.341 | S6: =COUNTIFS('4.a Simulation'!$BO$6:$BO$1005,">800",'4.a Simulation'!$BO$6:$BO$1005,"<=1000")/1000 -> 0.228 | T6: =COUNTIFS('4.a Simulation'!$BO$6:$BO$1005,">1000",'4.a Simulation'!$BO$6:$BO$1005,"<=1200")/1000 -> 0.004 | U6: =COUNTIFS('4.a Simulation'!$BO$6:$BO$1005,">1200")/1000 -> 0 | V6: =SUM(M6:U6) -> 1 | Z6: Probability | AA6: =COUNTIF('4.a Simulation'!$DU$6:$DU$1005,"<=-200")/1000 -> 0.136 | AB6: =COUNTIFS('4.a Simulation'!$DU$6:$DU$1005,">-200",'4.a Simulation'!$DU$6:$DU$1005,"<=0")/1000 -> 0.18 | AC6: =COUNTIFS('4.a Simulation'!$DU$6:$DU$1005,">0",'4.a Simulation'!$DU$6:$DU$1005,"<=200")/1000 -> 0.206 | AD6: =COUNTIFS('4.a Simulation'!$DU$6:$DU$1005,">200",'4.a Simulation'!$DU$6:$DU$1005,"<=400")/1000 -> 0.167 | AE6: =COUNTIFS('4.a Simulation'!$DU$6:$DU$1005,">400",'4.a Simulation'!$DU$6:$DU$1005,"<=600")/1000 -> 0.119 | AF6: =COUNTIFS('4.a Simulation'!$DU$6:$DU$1005,">600",'4.a Simulation'!$DU$6:$DU$1005,"<=800")/1000 -> 0.106 | AG6: =COUNTIFS('4.a Simulation'!$DU$6:$DU$1005,">800",'4.a Simulation'!$DU$6:$DU$1005,"<=1000")/1000 -> 0.063 | AH6: =COUNTIFS('4.a Simulation'!$DU$6:$DU$1005,">1000",'4.a Simulation'!$DU$6:$DU$1005,"<=1200")/1000 -> 0.018 | AI6: =COUNTIFS('4.a Simulation'!$DU$6:$DU$1005,">1200",'4.a Simulation'!$DU$6:$DU$1005,"<=1400")/1000 -> 0.005 | AJ6: =COUNTIF('4.a Simulation'!$DU$6:$DU$1005,">1400")/1000 -> 0 | AK6: =SUM(AA6:AJ6) -> 1
B7: Max Demand | C7: =_xlfn.MAXIFS('4.a Simulation'!$C$6:$C$1005,'4.a Simulation'!$Q$6:$Q$1005,"<=-200") -> 21.073584 | D7: =_xlfn.MAXIFS('4.a Simulation'!$C$6:$C$1005,'4.a Simulation'!$Q$6:$Q$1005,">-200",'4.a Simulation'!$Q$6:$Q$1005,"<=0") -> 33.494652 | E7: =_xlfn.MAXIFS('4.a Simulation'!$C$6:$C$1005,'4.a Simulation'!$Q$6:$Q$1005,">0",'4.a Simulation'!$Q$6:$Q$1005,"<=200") -> 32.685579 | F7: =_xlfn.MAXIFS('4.a Simulation'!$C$6:$C$1005,'4.a Simulation'!$Q$6:$Q$1005,">200",'4.a Simulation'!$Q$6:$Q$1005,"<=400") -> 34.020613 | G7: =_xlfn.MAXIFS('4.a Simulation'!$C$6:$C$1005,'4.a Simulation'!$Q$6:$Q$1005,">400",'4.a Simulation'!$Q$6:$Q$1005,"<=600") -> 31.484206 | H7: =_xlfn.MAXIFS('4.a Simulation'!$C$6:$C$1005,'4.a Simulation'!$Q$6:$Q$1005,">600") -> 0 | L7: Max Demand | M7: =_xlfn.MAXIFS('4.a Simulation'!$BA$6:$BA$1005,'4.a Simulation'!$BO$6:$BO$1005,"<=-200") -> 10.835483 | N7: =_xlfn.MAXIFS('4.a Simulation'!$BA$6:$BA$1005,'4.a Simulation'!$BO$6:$BO$1005,">-200",'4.a Simulation'!$BO$6:$BO$1005,"<0") -> 16.120488 | O7: =_xlfn.MAXIFS('4.a Simulation'!$BA$6:$BA$1005,'4.a Simulation'!$BO$6:$BO$1005,">0",'4.a Simulation'!$BO$6:$BO$1005,"<200") -> 18.128116 | P7: =_xlfn.MAXIFS('4.a Simulation'!$BA$6:$BA$1005,'4.a Simulation'!$BO$6:$BO$1005,">200",'4.a Simulation'!$BO$6:$BO$1005,"<400") -> 20.487759 | Q7: =_xlfn.MAXIFS('4.a Simulation'!$BA$6:$BA$1005,'4.a Simulation'!$BO$6:$BO$1005,">400",'4.a Simulation'!$BO$6:$BO$1005,"<600") -> 23.087307 | R7: =_xlfn.MAXIFS('4.a Simulation'!$BA$6:$BA$1005,'4.a Simulation'!$BO$6:$BO$1005,">600",'4.a Simulation'!$BO$6:$BO$1005,"<800") -> 27.317698 | S7: =_xlfn.MAXIFS('4.a Simulation'!$BA$6:$BA$1005,'4.a Simulation'!$BO$6:$BO$1005,">800",'4.a Simulation'!$BO$6:$BO$1005,"<1000") -> 27.574345 | T7: =_xlfn.MAXIFS('4.a Simulation'!$BA$6:$BA$1005,'4.a Simulation'!$BO$6:$BO$1005,">1000",'4.a Simulation'!$BO$6:$BO$1005,"<1200") -> 21.838776 | U7: =_xlfn.MAXIFS('4.a Simulation'!$BA$6:$BA$1005,'4.a Simulation'!$BO$6:$BO$1005,">1200") -> 0 | Z7: Max Demand | AA7: =_xlfn.MAXIFS('4.a Simulation'!$DG$6:$DG$1005,'4.a Simulation'!$DU$6:$DU$1005,"<-200") -> 8.2970393 | AB7: =_xlfn.MAXIFS('4.a Simulation'!$DG$6:$DG$1005,'4.a Simulation'!$DU$6:$DU$1005,">-200",'4.a Simulation'!$DU$6:$DU$1005,"<0") -> 10.03532 | AC7: =_xlfn.MAXIFS('4.a Simulation'!$DG$6:$DG$1005,'4.a Simulation'!$DU$6:$DU$1005,">0",'4.a Simulation'!$DU$6:$DU$1005,"<200") -> 10.139516 | AD7: =_xlfn.MAXIFS('4.a Simulation'!$DG$6:$DG$1005,'4.a Simulation'!$DU$6:$DU$1005,">200",'4.a Simulation'!$DU$6:$DU$1005,"<400") -> 10.335128 | AE7: =_xlfn.MAXIFS('4.a Simulation'!$DG$6:$DG$1005,'4.a Simulation'!$DU$6:$DU$1005,">400",'4.a Simulation'!$DU$6:$DU$1005,"<600") -> 10.072555 | AF7: =_xlfn.MAXIFS('4.a Simulation'!$DG$6:$DG$1005,'4.a Simulation'!$DU$6:$DU$1005,">600",'4.a Simulation'!$DU$6:$DU$1005,"<800") -> 9.2666272 | AG7: =_xlfn.MAXIFS('4.a Simulation'!$DG$6:$DG$1005,'4.a Simulation'!$DU$6:$DU$1005,">800",'4.a Simulation'!$DU$6:$DU$1005,"<1000") -> 9.039039 | AH7: =_xlfn.MAXIFS('4.a Simulation'!$DG$6:$DG$1005,'4.a Simulation'!$DU$6:$DU$1005,">1000",'4.a Simulation'!$DU$6:$DU$1005,"<1200") -> 9.7333605 | AI7: =_xlfn.MAXIFS('4.a Simulation'!$DG$6:$DG$1005,'4.a Simulation'!$DU$6:$DU$1005,">1200",'4.a Simulation'!$DU$6:$DU$1005,"<1400") -> 8.8531065 | AJ7: =_xlfn.MAXIFS('4.a Simulation'!$DG$6:$DG$1005,'4.a Simulation'!$DU$6:$DU$1005,">1400") -> 0
W16: S
